Workbook
Name BB: #REF!
Name CCC: #REF!
Name div: 'BD jeans Dama'!#REF!
Name his: #REF!
Name hist: #REF!
Name JEAN: 'BD jeans Dama'!#REF!
Name jeandama: 'BD jeans Dama'!#REF!
Name jeanss: 'BD jeans Dama'!#REF!
Name jeansss: 'BD jeans Dama'!$A$1:$F$4062
Name jn: 'BD jeans Dama'!#REF!
Name jnss: 'BD jeans Dama'!$A$2:$F$536
Name L: 'BASE DE DATOS OFICIAL'!$A$1:$D$126
Name mahis: #REF!
Name matof: 'BASE DE DATOS OFICIAL'!$A$16:$AF$371
Name matrix: #REF!
Name matrizoficial: 'BASE DE DATOS OFICIAL'!$16:$65452
Name MAX: #REF!
Name MAXX: #REF!
Name PLANILLA: #REF!
Name PLANILLA1: 'BASE DE DATOS OFICIAL'!$A$3:$CU$373
Name PLANILLA2: #REF!
Name PLANILLAMOD: 'BASE DE DATOS OFICIAL'!$A$16:$V$122
Name RUT: #REF!
Name RUTES: #REF!
Name VENTAS: #REF!
Name jeans: 'BD jeans Dama'!$A$1:$F$440
Name jeans2: 'BD jeans Dama'!$B$1:$I$440

Sheet TOMA DE PEDIDOS
E1: TRANSPORTE | H1: RAZON SOCIAL | L1: =_xlfn.IFNA(VLOOKUP(L5,'BASE DE DATOS OFICIAL'!$A$4:$AC$166,3,0),"SIN INFORMACIÓN")
H2: GIRO | L2: =_xlfn.IFNA(VLOOKUP(L5,'BASE DE DATOS OFICIAL'!$A$4:$AC$166,19,0),"SIN INFORMACIÓN")
E3: =VLOOKUP(L5,'BASE DE DATOS OFICIAL'!A3:AC166,14,0) | H3: DIRECCION | L3: =_xlfn.IFNA(VLOOKUP(L5,'BASE DE DATOS OFICIAL'!$A$4:$AC$166,5,0),"SIN INFORMACIÓN")
H4: NOMBRE TIENDA | L4: =_xlfn.IFNA(VLOOKUP(L5,'BASE DE DATOS OFICIAL'!$A$4:$AC$166,20,0),"SIN INFORMACIÓN")
E5: CONDICIONES DE PAGO | H5: RUT | Q5: FECHA
H6: COMUNA | L6: =_xlfn.IFNA(VLOOKUP(L5,'BASE DE DATOS OFICIAL'!$A$4:$AC$166,21,0),"SIN INFORMACIÓN") | Q6: CIUDAD | S6: =_xlfn.IFNA(VLOOKUP(L5,'BASE DE DATOS OFICIAL'!$A$4:$AC$166,4,0),"SIN INFORMACIÓN")
C7: MANUFACTURAS e IMPORTACIONES | E7: =_xlfn.IFNA(VLOOKUP(L5,'BASE DE DATOS OFICIAL'!$A$4:$AC$166,17,0),"SIN INFORMACIÓN") | H7: TELEFONO | L7: =_xlfn.IFNA(VLOOKUP(L5,'BASE DE DATOS OFICIAL'!$A$4:$AC$166,6,0),"SIN INFORMACIÓN") | Q7: CELULAR | S7: =_xlfn.IFNA(VLOOKUP(L5,'BASE DE DATOS OFICIAL'!$A$4:$AC$166,18,0),"SIN INFORMACIÓN")
C8: TITANIUM CHILE SPA | H8: ATENCION | L8: =TODAY() | Q8: E-MAIL | S8: =_xlfn.IFNA(VLOOKUP(L5,'BASE DE DATOS OFICIAL'!$A$4:$AC$166,9,0),"SIN INFORMACIÓN")
E9: NOTA DE PEDIDO | H9: VENDEDOR | L9: =_xlfn.IFNA(VLOOKUP(L5,'BASE DE DATOS OFICIAL'!$A$4:$AC$166,7,0),"SIN INFORMACIÓN") | Q9: ORDEN DE COMPRA | S9: 43 ALTO INVIERNO
C10: Av. Peru 710, Recoleta-Santiago | H10: TEMPORADA | L10: OTOÑO INVIERNO 2026
C11: www.mohicano.cl | E11: 143011 | H11: VENTA SUGERIDA | L11: =_xlfn.IFNA(VLOOKUP(L5,'BASE DE DATOS OFICIAL'!$A$4:$AC$166,29,0),"SIN INFORMACIÓN") | N11: prendas | Q11: DESCUENTO
H12: COLE. ANTERIOR | L12: PEDIDO REALIZADO | Q12: DESPACHO | S12: SALDO | T12: VALOR
H13: 3800 | L13: =_xlfn.IFNA(VLOOKUP(L5,'BASE DE DATOS OFICIAL'!$A$4:$AC$166,24,0),"SIN INFORMACIÓN") | Q13: =_xlfn.IFNA(VLOOKUP(L5,'BASE DE DATOS OFICIAL'!$A$4:$AC$166,25,0),"SIN INFORMACIÓN") | S13: =_xlfn.IFNA(VLOOKUP(L5,'BASE DE DATOS OFICIAL'!$A$4:$AC$166,26,0),"SIN INFORMACIÓN") | T13: =_xlfn.IFNA(VLOOKUP(L5,'BASE DE DATOS OFICIAL'!$A$4:$AC$166,28,0),"SIN INFORMACIÓN")
A14: BARRA | B14: CÓDIGO | C14: ARTÍCULO | D14: TIRO | E14: CORTE | F14: 36 | G14: 38 | H14: 40 | I14: 42 | J14: 44 | K14: 46 | L14: 48 | M14: 50 | N14: S | O14: M | P14: L | Q14: PRENDAS | S14: VALOR | T14: TOTAL
C15: =IF(B15<>"",VLOOKUP(B15,jeans2,2,FALSE),IF(A15<>"",VLOOKUP(A15,jeans,3,FALSE),"")) | D15: =IF(B15<>"",VLOOKUP(B15,jeans2,3,FALSE),IF(A15<>"",VLOOKUP(A15,jeans,4,FALSE),"")) | E15: =IF(B15<>"",VLOOKUP(B15,jeans2,4,FALSE),IF(A15<>"",VLOOKUP(A15,jeans,5,FALSE),"")) | Q15: =SUM($F15:$P15) | S15: =IF(B15<>"",VLOOKUP(B15,jeans2,5,FALSE),IF(A15<>"",VLOOKUP(A15,jeans,6,FALSE),"")) | T15: =IFERROR(Q15*S15,"")
C16: =IF(B16<>"",VLOOKUP(B16,jeans2,2,FALSE),IF(A16<>"",VLOOKUP(A16,jeans,3,FALSE),"")) | D16: =IF(B16<>"",VLOOKUP(B16,jeans2,3,FALSE),IF(A16<>"",VLOOKUP(A16,jeans,4,FALSE),"")) | E16: =IF(B16<>"",VLOOKUP(B16,jeans2,4,FALSE),IF(A16<>"",VLOOKUP(A16,jeans,5,FALSE),"")) | Q16: =SUM($F16:$P16) | S16: =IF(B16<>"",VLOOKUP(B16,jeans2,5,FALSE),IF(A16<>"",VLOOKUP(A16,jeans,6,FALSE),"")) | T16: =IFERROR(Q16*S16,"")
C17: =IF(B17<>"",VLOOKUP(B17,jeans2,2,FALSE),IF(A17<>"",VLOOKUP(A17,jeans,3,FALSE),"")) | D17: =IF(B17<>"",VLOOKUP(B17,jeans2,3,FALSE),IF(A17<>"",VLOOKUP(A17,jeans,4,FALSE),"")) | E17: =IF(B17<>"",VLOOKUP(B17,jeans2,4,FALSE),IF(A17<>"",VLOOKUP(A17,jeans,5,FALSE),"")) | Q17: =SUM($F17:$P17) | S17: =IF(B17<>"",VLOOKUP(B17,jeans2,5,FALSE),IF(A17<>"",VLOOKUP(A17,jeans,6,FALSE),"")) | T17: =IFERROR(Q17*S17,"")
C18: =IF(B18<>"",VLOOKUP(B18,jeans2,2,FALSE),IF(A18<>"",VLOOKUP(A18,jeans,3,FALSE),"")) | D18: =IF(B18<>"",VLOOKUP(B18,jeans2,3,FALSE),IF(A18<>"",VLOOKUP(A18,jeans,4,FALSE),"")) | E18: =IF(B18<>"",VLOOKUP(B18,jeans2,4,FALSE),IF(A18<>"",VLOOKUP(A18,jeans,5,FALSE),"")) | Q18: =SUM($F18:$P18) | S18: =IF(B18<>"",VLOOKUP(B18,jeans2,5,FALSE),IF(A18<>"",VLOOKUP(A18,jeans,6,FALSE),"")) | T18: =IFERROR(Q18*S18,"")
C19: =IF(B19<>"",VLOOKUP(B19,jeans2,2,FALSE),IF(A19<>"",VLOOKUP(A19,jeans,3,FALSE),"")) | D19: =IF(B19<>"",VLOOKUP(B19,jeans2,3,FALSE),IF(A19<>"",VLOOKUP(A19,jeans,4,FALSE),"")) | E19: =IF(B19<>"",VLOOKUP(B19,jeans2,4,FALSE),IF(A19<>"",VLOOKUP(A19,jeans,5,FALSE),"")) | Q19: =SUM($F19:$P19) | S19: =IF(B19<>"",VLOOKUP(B19,jeans2,5,FALSE),IF(A19<>"",VLOOKUP(A19,jeans,6,FALSE),"")) | T19: =IFERROR(Q19*S19,"")
C20: =IF(B20<>"",VLOOKUP(B20,jeans2,2,FALSE),IF(A20<>"",VLOOKUP(A20,jeans,3,FALSE),"")) | D20: =IF(B20<>"",VLOOKUP(B20,jeans2,3,FALSE),IF(A20<>"",VLOOKUP(A20,jeans,4,FALSE),"")) | E20: =IF(B20<>"",VLOOKUP(B20,jeans2,4,FALSE),IF(A20<>"",VLOOKUP(A20,jeans,5,FALSE),"")) | Q20: =SUM($F20:$P20) | S20: =IF(B20<>"",VLOOKUP(B20,jeans2,5,FALSE),IF(A20<>"",VLOOKUP(A20,jeans,6,FALSE),"")) | T20: =IFERROR(Q20*S20,"")
C21: =IF(B21<>"",VLOOKUP(B21,jeans2,2,FALSE),IF(A21<>"",VLOOKUP(A21,jeans,3,FALSE),"")) | D21: =IF(B21<>"",VLOOKUP(B21,jeans2,3,FALSE),IF(A21<>"",VLOOKUP(A21,jeans,4,FALSE),"")) | E21: =IF(B21<>"",VLOOKUP(B21,jeans2,4,FALSE),IF(A21<>"",VLOOKUP(A21,jeans,5,FALSE),"")) | Q21: =SUM($F21:$P21) | S21: =IF(B21<>"",VLOOKUP(B21,jeans2,5,FALSE),IF(A21<>"",VLOOKUP(A21,jeans,6,FALSE),"")) | T21: =IFERROR(Q21*S21,"")
C22: =IF(B22<>"",VLOOKUP(B22,jeans2,2,FALSE),IF(A22<>"",VLOOKUP(A22,jeans,3,FALSE),"")) | D22: =IF(B22<>"",VLOOKUP(B22,jeans2,3,FALSE),IF(A22<>"",VLOOKUP(A22,jeans,4,FALSE),"")) | E22: =IF(B22<>"",VLOOKUP(B22,jeans2,4,FALSE),IF(A22<>"",VLOOKUP(A22,jeans,5,FALSE),"")) | Q22: =SUM($F22:$P22) | S22: =IF(B22<>"",VLOOKUP(B22,jeans2,5,FALSE),IF(A22<>"",VLOOKUP(A22,jeans,6,FALSE),"")) | T22: =IFERROR(Q22*S22,"")
C23: =IF(B23<>"",VLOOKUP(B23,jeans2,2,FALSE),IF(A23<>"",VLOOKUP(A23,jeans,3,FALSE),"")) | D23: =IF(B23<>"",VLOOKUP(B23,jeans2,3,FALSE),IF(A23<>"",VLOOKUP(A23,jeans,4,FALSE),"")) | E23: =IF(B23<>"",VLOOKUP(B23,jeans2,4,FALSE),IF(A23<>"",VLOOKUP(A23,jeans,5,FALSE),"")) | Q23: =SUM($F23:$P23) | S23: =IF(B23<>"",VLOOKUP(B23,jeans2,5,FALSE),IF(A23<>"",VLOOKUP(A23,jeans,6,FALSE),"")) | T23: =IFERROR(Q23*S23,"")
C24: =IF(B24<>"",VLOOKUP(B24,jeans2,2,FALSE),IF(A24<>"",VLOOKUP(A24,jeans,3,FALSE),"")) | D24: =IF(B24<>"",VLOOKUP(B24,jeans2,3,FALSE),IF(A24<>"",VLOOKUP(A24,jeans,4,FALSE),"")) | E24: =IF(B24<>"",VLOOKUP(B24,jeans2,4,FALSE),IF(A24<>"",VLOOKUP(A24,jeans,5,FALSE),"")) | Q24: =SUM($F24:$P24) | S24: =IF(B24<>"",VLOOKUP(B24,jeans2,5,FALSE),IF(A24<>"",VLOOKUP(A24,jeans,6,FALSE),"")) | T24: =IFERROR(Q24*S24,"")
C25: =IF(B25<>"",VLOOKUP(B25,jeans2,2,FALSE),IF(A25<>"",VLOOKUP(A25,jeans,3,FALSE),"")) | D25: =IF(B25<>"",VLOOKUP(B25,jeans2,3,FALSE),IF(A25<>"",VLOOKUP(A25,jeans,4,FALSE),"")) | E25: =IF(B25<>"",VLOOKUP(B25,jeans2,4,FALSE),IF(A25<>"",VLOOKUP(A25,jeans,5,FALSE),"")) | Q25: =SUM($F25:$P25) | S25: =IF(B25<>"",VLOOKUP(B25,jeans2,5,FALSE),IF(A25<>"",VLOOKUP(A25,jeans,6,FALSE),"")) | T25: =IFERROR(Q25*S25,"")
C26: =IF(B26<>"",VLOOKUP(B26,jeans2,2,FALSE),IF(A26<>"",VLOOKUP(A26,jeans,3,FALSE),"")) | D26: =IF(B26<>"",VLOOKUP(B26,jeans2,3,FALSE),IF(A26<>"",VLOOKUP(A26,jeans,4,FALSE),"")) | E26: =IF(B26<>"",VLOOKUP(B26,jeans2,4,FALSE),IF(A26<>"",VLOOKUP(A26,jeans,5,FALSE),"")) | Q26: =SUM($F26:$P26) | S26: =IF(B26<>"",VLOOKUP(B26,jeans2,5,FALSE),IF(A26<>"",VLOOKUP(A26,jeans,6,FALSE),"")) | T26: =IFERROR(Q26*S26,"")
... C59: =IF(B59<>"",VLOOKUP(B59,jeans2,2,FALSE),IF(A59<>"",VLOOKUP(A59,jeans,3,FALSE),"")) | D59: =IF(B59<>"",VLOOKUP(B59,jeans2,3,FALSE),IF(A59<>"",VLOOKUP(A59,jeans,4,FALSE),"")) | E59: =IF(B59<>"",VLOOKUP(B59,jeans2,4,FALSE),IF(A59<>"",VLOOKUP(A59,jeans,5,FALSE),"")) | Q59: =SUM($F59:$P59) | S59: =IF(B59<>"",VLOOKUP(B59,jeans2,5,FALSE),IF(A59<>"",VLOOKUP(A59,jeans,6,FALSE),"")) | T59: =IFERROR(Q59*S59,"")
C60: =IF(B60<>"",VLOOKUP(B60,jeans2,2,FALSE),IF(A60<>"",VLOOKUP(A60,jeans,3,FALSE),"")) | D60: =IF(B60<>"",VLOOKUP(B60,jeans2,3,FALSE),IF(A60<>"",VLOOKUP(A60,jeans,4,FALSE),"")) | E60: =IF(B60<>"",VLOOKUP(B60,jeans2,4,FALSE),IF(A60<>"",VLOOKUP(A60,jeans,5,FALSE),"")) | F60: CANTIDAD TOTAL DE ARTICULOS | Q60: =SUM(Q15:Q59) | S60: =IF(B60<>"",VLOOKUP(B60,jeans2,5,FALSE),IF(A60<>"",VLOOKUP(A60,jeans,6,FALSE),"")) | T60: =IFERROR(Q60*S60,"")
B61: OBSERVACIONES | R61: Descuento especial: | S61: 0 | T61: =+T60*S61
S62: NETO | T62: =+T60-T61
B63: Autorizo para comunicar a terceros la mora o simple retardo de la obligación, en la base de datos SICOM | S63: IVA 19% | T63: =T62*19%
B64: (Sistema consolidado de morosidad y protesto) de DICOM S.A. o en cualquier otra base de datos de morosidades y protestos existentes | S64: TOTAL | T64: =T62+T63

Sheet Stock
A1: CODIGO | B1: TIRO | C1: BOTA | D1: COLOR | E1: 36 | F1: 38 | G1: 40 | H1: 42 | I1: 44 | J1: 46 | L1: CODIGO | M1: TIRO | N1: BOTA | O1: COLOR | P1: 36 | Q1: 38 | R1: 40 | S1: 42 | T1: 44 | U1: 46
A2: 423600 | B2: CINTURA | C2: PALAZZO | E2: 24 | F2: 46 | G2: 42 | H2: 41 | I2: 32 | J2: 25 | L2: 432900 | M2: MEDIO | N2: OXFORD | P2: 50 | Q2: 118 | R2: 125 | S2: 116 | T2: 83 | U2: 68
A3: 422200 | B3: MEDIO | C3: TOBILLERO | E3: 13 | F3: 60 | G3: 53 | H3: 48 | I3: 31 | L3: 431800 | M3: CINTURA | N3: WIDE | P3: 56 | Q3: 117 | R3: 127 | S3: 98 | T3: 79 | U3: 54
A4: 423500 | B4: CINTURA | C4: PITILLO | E4: 8 | F4: 31 | G4: 31 | H4: 31 | I4: 26 | J4: 11 | L4: 430900 | M4: CINTURA | N4: FLARE | P4: 18 | Q4: 51 | R4: 55 | S4: 48 | T4: 35 | U4: 26
A5: 420301 | B5: MEDIO | C5: TOBILLERO | E5: 7 | F5: 24 | G5: 27 | H5: 29 | I5: 14 | J5: 4 | L5: 432300 | M5: CINTURA | N5: WIDE LEG | P5: 56 | Q5: 115 | R5: 132 | S5: 122 | T5: 85 | U5: 66
A6: 420600 | B6: CINTURA | C6: PITILLO | E6: 24 | F6: 3 | H6: 10 | I6: 18 | J6: 8
A7: 420100 | B7: CINTURA | C7: PITILLO | E7: 27 | F7: 22 | G7: 52 | H7: 12 | I7: 8
A8: 424400 | B8: CINTURA | C8: PITILLO | E8: 27 | F8: 27 | G8: 24 | H8: 32
A9: 422300 | B9: MEDIO | C9: FLARE | E9: 18 | F9: 19 | G9: 11 | H9: 19 | I9: 16
A10: 420300 | B10: MEDIO | C10: TOBILLERO | E10: 13 | F10: 15 | G10: 16 | H10: 15 | I10: 11 | J10: 10
A11: 420400 | B11: MEDIO | C11: FLARE | E11: 26 | F11: 6 | G11: 9 | H11: 7 | I11: 8 | J11: 16
A12: 423200 | B12: CINTURA | C12: OXFORD | E12: 13 | F12: 1 | G12: 17 | H12: 14 | I12: 12 | J12: 14
A13: 422500 | B13: CINTURA | C13: FLARE | E13: 8 | G13: 12 | H13: 15 | I13: 13 | J13: 17
A14: 424600 | B14: CINTURA | C14: TOBILLERO | E14: 4 | F14: 4 | G14: 22 | H14: 17 | I14: 17
A15: 422800 | B15: MEDIO | C15: FLARE | F15: 4 | G15: 29 | I15: 28
A16: 422000 | B16: CINTURA | C16: PITILLO | E16: 34 | F16: 10 | G16: 11 | H16: 3 | I16: 3
A17: 423316 | B17: CINTURA | C17: TOBILLERO | E17: 6 | F17: 14 | G17: 14 | H17: 13 | I17: 8 | J17: 4
A18: 422101 | B18: CINTURA | C18: PITILLO | E18: 14 | F18: 1 | G18: 15 | H18: 9 | I18: 14
A19: 421400 | B19: CINTURA | C19: OXFORD | E19: 7 | F19: 0 | G19: 1 | H19: 1 | I19: 12 | J19: 32
A20: 420800 | B20: CINTURA | C20: FLARE | E20: 6 | F20: 10 | G20: 12 | H20: 12 | I20: 6 | J20: 6
A21: 421801 | B21: CINTURA | C21: FLARE | G21: 2 | H21: 3 | I21: 13 | J21: 10
A22: 420160 | B22: CINTURA | C22: PITILLO | D22: CLARO | E22: 7 | F22: 12 | G22: 9 | H22: 10 | I22: 6 | J22: 5
A23: 421100 | B23: CINTURA | C23: FLARE | E23: 3 | F23: 4 | G23: 6 | H23: 6 | I23: 20 | J23: 7
A24: 422700 | B24: CINTURA | C24: RECTO | E24: 10 | F24: 14 | G24: 6 | I24: 6 | J24: 10
A25: 423000 | B25: CINTURA | C25: PALAZZO | E25: 10 | H25: 4 | I25: 21 | J25: 9
A26: 424900 | B26: CINTURA | C26: PALAZZO | D26: negro | E26: 4 | F26: 12 | G26: 13 | H26: 6 | I26: 3 | J26: 0
A27: 424900 | B27: CINTURA | C27: PALAZZO | D27: GRIS | E27: 9 | F27: 14 | G27: 15 | H27: 6 | I27: 4 | J27: 4
A28: 421000 | B28: MEDIO | C28: OXFORD | E28: 5 | F28: 15 | G28: 17 | H28: 16 | I28: 11 | J28: 12
A29: 424000 | B29: CINTURA | C29: PITILLO | E29: 20 | G29: 3 | I29: 10
A30: 422701 | B30: CINTURA | C30: RECTO | E30: 1 | H30: 4 | I30: 11 | J30: 14
A31: 423448 | B31: CINTURA | C31: FLARE | I31: 4
A32: 420101 | B32: CINTURA | C32: PITILLO | E32: 7 | F32: 7 | G32: 7 | H32: 7 | J32: 2
A33: 424701 | B33: CINTURA | C33: RECTO | E33: 2 | G33: 13 | I33: 13
A34: 421901 | B34: CINTURA | C34: PITILLO | E34: 4 | F34: 8 | G34: 6 | H34: 5 | I34: 4 | J34: 1
A35: 422900 | B35: CINTURA | C35: PITILLO | E35: 23 | F35: 1 | I35: 2
A36: 421902 | B36: CINTURA | C36: PITILLO | E36: 2 | F36: 6 | G36: 6 | H36: 5 | I36: 4 | J36: 2
A37: 420501 | B37: CINTURA | C37: OXFORD | E37: 4 | F37: 1 | G37: 5 | H37: 1 | I37: 6 | J37: 4
A38: 422190 | B38: CINTURA | C38: TOBILLERO | D38: GLITEE | E38: 2 | F38: 5 | G38: 5 | H38: 5 | I38: 3 | J38: 3
A39: 421900 | B39: CINTURA | C39: PITILLO | E39: 0 | F39: 4 | G39: 7 | H39: 3 | I39: 8
A40: 423501 | B40: CINTURA | C40: PITILLO | E40: 2 | F40: 6 | G40: 1 | H40: 6 | I40: 2 | J40: 6
A41: 423308 | B41: CINTURA | C41: TOBILLERO | F41: 5 | G41: 3 | H41: 4 | I41: 9
A42: 423408 | B42: CINTURA | C42: FLARE | F42: 14 | H42: 2 | I42: 4
A43: 424801 | B43: CINTURA | C43: RECTO | E43: 4 | G43: 10 | I43: 9
A44: 420900 | B44: MEDIO | C44: PITILLO | F44: 5 | I44: 4 | J44: 10
A45: 423900 | B45: CINTURA | C45: FLARE | E45: 2 | G45: 9 | I45: 8
A46: 422100 | B46: CINTURA | C46: TOBILLERO | I46: 5 | J46: 13
A47: 424500 | B47: CINTURA | C47: PITILLO | E47: 4 | H47: 3 | I47: 3
A48: 424700 | B48: CINTURA | C48: RECTO | E48: 11 | F48: 1 | J48: 5
A49: 420802 | B49: CINTURA | C49: FLARE | F49: 1 | G49: 5 | H49: 5 | I49: 3 | J49: 3
A50: 420200 | B50: CINTURA | C50: RECTO | F50: 1 | G50: 1 | I50: 2 | J50: 11
A51: 421301 | B51: CINTURA | C51: OXFORD | E51: 3 | G51: 6 | H51: 2 | I51: 4
A52: 424300 | B52: CINTURA | C52: PITILLO | F52: 5 | G52: 2 | H52: 3 | J52: 6
A53: 421402 | B53: CINTURA | C53: OXFORD | F53: 3 | G53: 1 | H53: 4 | I53: 3 | J53: 2
A54: 425600 | B54: CINTURA | C54: PALAZZO | E54: 2 | I54: 2 | J54: 7
A55: 423304 | B55: CINTURA | C55: TOBILLERO | I55: 6 | J55: 2
A56: 421300 | B56: CINTURA | C56: OXFORD | E56: 2 | H56: 4 | J56: 4
A57: 424960 | B57: CINTURA | C57: PALAZZO | E57: 1 | F57: 2 | G57: 2 | H57: 2 | I57: 1 | J57: 1
A58: 421800 | B58: CINTURA | C58: FLARE | G58: 3 | H58: 2 | I58: 2 | J58: 1
A59: 423348 | B59: CINTURA | C59: TOBILLERO | F59: 2 | G59: 2 | H59: 1 | I59: 3
A60: 422601 | B60: MEDIO | C60: PITILLO | I60: 7
A61: 421401 | B61: CINTURA | C61: OXFORD | F61: 2 | G61: 4 | J61: 1
A62: 421001 | B62: MEDIO | C62: RECTO | G62: 2 | H62: 1 | I62: 1 | J62: 2
A63: 420500 | B63: CINTURA | C63: OXFORD | F63: 1 | G63: 2 | I63: 2
A64: 420402 | B64: MEDIO | C64: FLARE | I64: 5
A65: 423416 | B65: CINTURA | C65: FLARE | E65: 1 | G65: 1 | I65: 2
A66: 422600 | B66: MEDIO | C66: PITILLO | J66: 3
A67: 423309 | B67: CINTURA | C67: TOBILLERO | F67: 1 | G67: 1 | H67: 1
A68: 422400 | B68: MEDIO | C68: OXFORD | I68: 2
A69: 422401 | B69: MEDIO | C69: OXFORD
A70: 423800 | B70: CINTURA | C70: PALAZZO
A71: 424200 | B71: CINTURA | C71: PALAZZO | F71: 1 | H71: 9 | I71: 1 | J71: 3
A72: 423409 | B72: CINTURA | C72: FLARE
A73: 423404 | B73: CINTURA | C73: FLARE
A74: 420801 | B74: CINTURA | C74: FLARE
A75: 420160 | B75: CINTURA | C75: PITILLO | D75: OSCURO

Sheet Hoja2

Sheet Hoja1

Sheet BD jeans Dama
A1: ARTICULO | B1: CODIGO | C1: DESCRIPCIÓN | D1: TIRO | E1: BOTA | F1: PRECIO
A2: 3801 | B2: 3801 | C2: Pretina revés, doble bolsillo relojero, cierre bota | D2: Cintura | E2: Tobillero | F2: 24990
A3: 3802 | B3: 3802 | C3: Smart Denim pinza costado sin basta | D3: Cintura | E3: Oxford | F3: 25990
A4: 3818 | B4: 3818 | C4: Marengo con roturas láser | D4: Cintura | E4: Recto | F4: 24990
A5: 3821-00 | B5: 3821-00 | C5: Imprentado biodesgastado | D5: Medio | E5: Oxford | F5: 24990
A6: 3821-01 | B6: 3821-01 | C6: Bolsillo delantero, costura ancha, Imprentado ox. | D6: Medio | E6: Oxford | F6: 24990
A7: 3826 | B7: 3826 | C7: Vestido negro con cinturón | D7: Vestido | E7: Muslo | F7: 28990
A8: 3832-09 | B8: 3832-09 | C8: Verde con pretina desflecada | D8: Cintura | E8: Palazzo | F8: 26990
A9: 3834 | B9: 3834 | C9: Clásico 5 bolsillos, gris con repaso costura | D9: Cintura | E9: Palazzo | F9: 26990
A10: 3837 | B10: 3837 | C10: Cargo negro Eco Cuero | D10: Cintura | E10: Recto | F10: 26990
A11: 3840 | B11: 3840 | C11: Clásico gris gravillado, bolsillos traseros curvos | D11: Cintura | E11: Flare | F11: 25990
A12: 3846-04 | B12: 3846-04 | C12: Cargo 4 bolsillos color chocolate | D12: Medio | E12: Palazzo | F12: 26990
A13: 3846-06 | B13: 3846-06 | C13: Cargo 4 bolsillos teñido orgánico con nueces | D13: Medio | E13: Palazzo | F13: 26990
A14: 3846-09 | B14: 3846-09 | C14: Cargo 4 bolsillos color Verde Oliva | D14: Medio | E14: Palazzo | F14: 26990
A15: 3846-38 | B15: 3846-38 | C15: Cargo 4 bolsillos color Ostra | D15: Medio | E15: Palazzo | F15: 26990
A16: 3846-71 | B16: 3846-71 | C16: Cargo 4 bolsillos color Terracota | D16: Medio | E16: Palazzo | F16: 26990
A17: 3849 | B17: 3849 | C17: Clásico | D17: Cintura | E17: Pitillo | F17: 24990
A18: 3853-04 | B18: 3853-04 | C18: Cargo/cinturón chocolate hilo al tono | D18: Cintura | E18: Oxford | F18: 26990
A19: 3851 | B19: 3851 | C19: Pieza lateral | D19: Cintura | E19: Palazzo | F19: 26990
A20: 3857 | B20: 3857 | C20: Azúl focalizado tenue, pinzas delanteras y traseras | D20: Cintura | E20: Pitillo | F20: 24990
A21: 3858 | B21: 3858 | C21: Wide Leg marengo | D21: Cintura | E21: Recto/ Cargo | F21: 26990
A22: 3859 | B22: 3859 | C22: Casaca oversize, bordado, gravillado | D22: Casaca | F22: 25990
A23: 3860 | B23: 3860 | C23: Corte diagonal en pretina | D23: Medio | E23: Tobillero | F23: 24990
A24: 3861 | B24: 3861 | C24: HIGH WAIST sin pinza | D24: Cintura | E24: Recto | F24: 24990
A25: 3862-00 | B25: 3862-00 | C25: Clásico color negro bolsillos traseros ovalados | D25: Medio | E25: Recto | F25: 24990
A26: 3862-01 | B26: 3862-01 | C26: Clásico Gris focalizado bolsillos traseros ovalados | D26: Medio | E26: Recto | F26: 24990
A27: 3865 | B27: 3865 | C27: Push in push up azúl focalizado | D27: Cintura | E27: Flare | F27: 25990
A28: 3869 | B28: 3869 | C28: Negro pestaña bolsillo delantero | D28: Cintura | E28: Flare | F28: 25990
A29: 3870 | B29: 3870 | C29: Casaca oversize con tapetas, gravillado | D29: Casaca | F29: 26990
A30: 3871-00 | B30: 3871-00 | C30: Pretina ancha con doble botón Bio Medio | D30: Cintura | E30: Pitillo | F30: 24990
A31: 3871-01 | B31: 3871-01 | C31: Pretina ancha c/doble botón, focalizado oxidado | D31: Cintura | E31: Pitillo | F31: 24990
A32: 3877 | B32: 3877 | C32: Negro con aplicación Lumen | D32: Cintura | E32: Pitillo | F32: 24990
A33: 3878 | B33: 3878 | C33: Pretina desflecada sin basta desflecada | D33: Cintura | E33: Palazzo | F33: 26990
A34: 3879 | B34: 3879 | C34: Tajali en bota, pieza en altura bigotes | D34: Medio | E34: Tobillero | F34: 24990
A35: 3880 | B35: 3880 | C35: Smart Denim roturas delanteras | D35: Cintura | E35: Tobillero | F35: 24990
A36: 3882-00 | B36: 3882-00 | C36: Marengo gravillado 2 pasadores, pinza lateral | D36: Cintura | E36: Recto | F36: 24990
A37: 3882-01 | B37: 3882-01 | C37: Negro 2 pasadores, pinza lateral | D37: Cintura | E37: Recto | F37: 24990
A38: 3883 | B38: 3883 | C38: Clásico 5 bolsillos bolsillo trasero destroyed | D38: Cintura | E38: Recto | F38: 24990
A39: 3886 | B39: 3886 | C39: Wide Leg azúl focalizado tenue | D39: Cintura | E39: Palazzo | F39: 26990
A40: 3888 | B40: 3888 | C40: Cargo azúl, con bolsillos carpinteros | D40: Cintura | E40: Recto | F40: 26990
A41: 3889 | B41: 3889 | C41: Azúl focalizado 2 pasadores atraque V | D41: Cintura | E41: Oxford | F41: 25990
A42: 3891 | B42: 3891 | C42: Cargo 4 bolsillos, Bolsillo Argentino | D42: Cintura | E42: Flare | F42: 26990
A43: 3892-00 | B43: 3892-00 | C43: Cargo 4 bolsillos Gravillado celeste | D43: Cintura | E43: Recto | F43: 26990
A44: 3892-01 | B44: 3892-01 | C44: Cargo 4 bolsillos Bio Focalizado azúl | D44: Cintura | E44: Recto | F44: 26990
A45: 3893 | B45: 3893 | C45: Cargo Gris gravillado | D45: Cintura | E45: Palazzo | F45: 26990
A46: 3896 | B46: 3896 | C46: Casaca clásica, aplicación eco cuero | D46: Casaca | E46: Negro | F46: 27990
A47: 3897 | B47: 3897 | C47: Negro Eco Cuero | D47: Cintura | E47: Flare | F47: 25990
A48: 3898 | B48: 3898 | C48: Clásico Eco Cuero | D48: Cintura | E48: Pitillo | F48: 24990
A49: 3894-00 | B49: 3894-00 | C49: Clásico azúl bolsillos traseros ovalados | D49: Cintura | E49: Pitillo | F49: 24990
A50: 3894-01 | B50: 3894-01 | C50: Clásico azúl bols. tras. ovalados c/repaso costura | D50: Cintura | E50: Pitillo | F50: 24990
A51: 3150 | B51: 3150 | C51: Clásico Oxidado | D51: Cintura | E51: Pitillo | F51: 24990
A52: X3805 | B52: X3805 | C52: Corte pierna | D52: Cintura | E52: Flare | F52: 25990
A53: X3875 | B53: X3875 | C53: Smart Denim, azul focalizado tenue | D53: Cintura | E53: Flare | F53: 25990
A54: X3895 | B54: X3895 | C54: Roturas delanteras y bolsillos traseros | D54: Cintura | E54: Recto | F54: 24990
A55: X123826 | B55: X123826 | C55: Vestido Negro Cinturon | D55: Vestido | F55: 28990
A56: 3633 | B56: 3633 | C56: Jean clásico | D56: Cintura | E56: Pitillo | F56: 24990
A57: 3802 | B57: 3802 | C57: Basta deflecada | D57: Cintura | E57: Oxford | F57: 25990
A58: 3862 | B58: 3862 | C58: Clásico | D58: Medio | E58: Recto | F58: 24990
A59: 3865-00 | B59: 3865-00 | C59: Push in Push up azul oscuro | D59: Cintura | E59: Flare | F59: 25990
A60: 3865-01 | B60: 3865-01 | C60: Push in Push up lavado claro | D60: Cintura | E60: Flare | F60: 25990
A61: 3878-00 | B61: 3878-00 | C61: Smart Denim azul oscuro | D61: Cintura | E61: Tobillero | F61: 24990
A62: 3878-01 | B62: 3878-01 | C62: Smart Denim lavado claro | D62: Cintura | E62: Tobillero | F62: 24990
A63: 3880 | B63: 3880 | C63: Clásico | D63: Cintura | E63: Tobillero | F63: 24990
A64: 3882 | B64: 3882 | C64: Bordado | D64: Cintura | E64: Recto | F64: 24990
A65: 3894 | B65: 3894 | C65: Clásico | D65: Cintura | E65: Pitillo | F65: 24990
A66: 3902 | B66: 3902 | C66: Smart denim bolsillos redondos | D66: Cintura | E66: Recto | F66: 24990
A67: 3904 | B67: 3904 | C67: Bolsillo con tapeta sobre pretina | D67: Cadera | E67: Palazzo | F67: 24990
A68: 3905 | B68: 3905 | C68: Detalle pierna + bolsillos rectos | D68: Cintura | E68: Flare | F68: 25990
A69: 3906 | B69: 3906 | C69: Detalles en boca de bolsillos | D69: Medio | E69: Oxford | F69: 25990
A70: 3915 | B70: 3915 | C70: Smart denim bordado | D70: Cintura | E70: Pitillo | F70: 24990
A71: 3919-00 | B71: 3919-00 | C71: Cinturón de tela + tajalí | D71: Cintura | E71: Tobillero | F71: 25990
A72: 3919-01 | B72: 3919-01 | C72: Cinturón de tela + tajalí+glitter | D72: Cintura | E72: Tobillero | F72: 25990
A73: 3921 | B73: 3921 | C73: Bolsillos costuras 1/8 | D73: Cintura | E73: Pitillo | F73: 24990
A74: 3922 | B74: 3922 | C74: Bolsillos carpinteros y cinturón | D74: Cintura | E74: Flare | F74: 25990
A75: 3932 | B75: 3932 | C75: Relojeros de tope+2 tonos de hilo | D75: Medio | E75: Pitillo | F75: 24990
A76: 3937 | B76: 3937 | C76: Relojeros de tope + bordados | D76: Cintura | E76: Oxford | F76: 26990
A77: 3940 | B77: 3940 | C77: Cargo + bolsillos parche (argentino) | D77: Cintura | E77: Recto | F77: 24990
A78: 3941 | B78: 3941 | C78: Aplicaciones lumen | D78: Cintura | E78: Pitillo | F78: 24990
A79: 3944 | B79: 3944 | C79: Bolsillos con tapeta | D79: Cintura | E79: Palazzo | F79: 26990
A80: 3947 | B80: 3947 | C80: Push in Push up + bordados | D80: Cintura | E80: Flare | F80: 25990
A81: 3950-00 | B81: 3950-00 | C81: Pliegue en bolsillos y relojero | D81: Cintura | E81: Flare | F81: 25990
A82: 3950-01 | B82: 3950-01 | C82: Pliegue en bolsillos y relojero | D82: Cintura | E82: Flare | F82: 25990
A83: 3950-02 | B83: 3950-02 | C83: Pliegue en bolsillos y relojero | D83: Cintura | E83: Flare | F83: 25990
A84: 3954-00 | B84: 3954-00 | C84: Pliegue en bolsillos y relojero | D84: Cintura | E84: Palazzo | F84: 25990
A85: 3954-01 | B85: 3954-01 | C85: Pliegue en bolsillos y relojero | D85: Cintura | E85: Palazzo | F85: 25990
A86: 3954-02 | B86: 3954-02 | C86: Pliegue en bolsillos y relojero | D86: Cintura | E86: Palazzo | F86: 25990
A87: 3955 | B87: 3955 | C87: Clásico Push in Push up | D87: Cintura | E87: Palazzo | F87: 26990
A88: 3957 | B88: 3957 | C88: Aplicaciones lumen | D88: Cintura | E88: Pitillo | F88: 25990
A89: 3958-00 | B89: 3958-00 | C89: Eco Cuero Negro | D89: Cintura | E89: Palazzo | F89: 28990
A90: 3958-01 | B90: 3958-01 | C90: Eco Cuero Café | D90: Cintura | E90: Palazzo | F90: 28990
A91: 3960-00 | B91: 3960-00 | C91: Pliegue en bolsillos y relojero | D91: Cintura | E91: Palazzo | F91: 24990
A92: 3960-01 | B92: 3960-01 | C92: Pliegue en bolsillos y relojero | D92: Cintura | E92: Palazzo | F92: 24990
A93: 3961 | B93: 3961 | C93: Clásico 2 tonos de hilo | D93: Cintura | E93: Pitillo | F93: 23990
A94: 3962 | B94: 3962 | C94: Relojeros de tope | D94: Cintura | E94: Recto | F94: 23990
A95: 3966-00 | B95: 3966-00 | C95: Leopardo oscuro | D95: Medio | E95: Palazzo | F95: 28990
A96: 3967 | B96: 3967 | C96: Tabaco | D96: Cintura | E96: Palazzo | F96: 25990
A97: 3968 | B97: 3968 | C97: Vino | D97: Cintura | E97: Pitillo | F97: 24990
A98: 3969-00 | B98: 3969-00 | C98: Leopardo claro | D98: Cintura | E98: Flare | F98: 28990
A99: 3969-01 | B99: 3969-01 | C99: Cebra | D99: Cintura | E99: Flare | F99: 28990
A100: 3970-00 | B100: 3970-00 | C100: Vaca verde oliva | D100: Medio | E100: Palazzo | F100: 28990
...

Sheet Cálculo Intereses
A1: RUT | C1: Nombre
A3: Capital adeudado | B3: 8000000
A5: Pié | B5: 5000000
A6: Cuotas | B6: 6
A7: Interés | B7: 0.02
A8: Inicio de fecha | B8: 46183
A9: Valor Intereses | B9: =(($B$3-$B$5)*$B$7)*$B$6
A11: Cuota | B11: Fecha | C11: Valor
A12: =($B$6)-($B$6-1) | B12: =+B8 | C12: =IF(A12<>"-",(($B$3-$B$5)/10+($B$9/$B$6)),"-")
A13: =IF($B$6=2,"2",IF($B$6<2,"-","2")) | B13: =IF(A13<>"-",B12+30,"-") | C13: =IF(A13<>"-",(($B$3-$B$5)/10+($B$9/$B$6)),"-")
A14: =IF($B$6=3,"3",IF($B$6<3,"-","3")) | B14: =IF(A14<>"-",B13+30,"-") | C14: =IF(A14<>"-",(($B$3-$B$5)/10+($B$9/$B$6)),"-")
A15: =IF($B$6=4,"4",IF($B$6<4,"-","4")) | B15: =IF(A15<>"-",B14+30,"-") | C15: =IF(A15<>"-",(($B$3-$B$5)/10+($B$9/$B$6)),"-")
A16: =IF($B$6=5,"5",IF($B$6<5,"-","5")) | B16: =IF(A16<>"-",B15+30,"-") | C16: =IF(A16<>"-",(($B$3-$B$5)/10+($B$9/$B$6)),"-")
A17: =IF($B$6=6,"6",IF($B$6<6,"-","6")) | B17: =IF(A17<>"-",B16+30,"-") | C17: =IF(A17<>"-",(($B$3-$B$5)/10+($B$9/$B$6)),"-")
A18: =IF($B$6=7,"7",IF($B$6<7,"-","7")) | B18: =IF(A18<>"-",B17+30,"-") | C18: =IF(A18<>"-",(($B$3-$B$5)/10+($B$9/$B$6)),"-")
A19: =IF($B$6=8,"8",IF($B$6<8,"-","8")) | B19: =IF(A19<>"-",B18+30,"-") | C19: =IF(A19<>"-",(($B$3-$B$5)/10+($B$9/$B$6)),"-")
A20: =IF($B$6=9,"9",IF($B$6<9,"-","9")) | B20: =IF(A20<>"-",B19+30,"-") | C20: =IF(A20<>"-",(($B$3-$B$5)/10+($B$9/$B$6)),"-")
A21: =IF($B$6=10,"10",IF($B$6<10,"-","10")) | B21: =IF(A21<>"-",B20+30,"-") | C21: =IF(A21<>"-",(($B$3-$B$5)/10+($B$9/$B$6)),"-")
C22: =SUM(C12:C21)

Sheet Hoja3
A1: 436500 | B1: Jeans Cintura recto, Smart Denim, doble pasador delantero. | C1: Cintura | D1: Recto | E1: 25990 | F1: 3902
A2: 436204 | B2: Jeans Cintura Pitillo colores, Clásico, pasador alto CAFÉ | C2: Cintura | D2: Pitillo | E2: 25990 | F2: 4233/ colores | G2: Descargar
A3: 436206 | B3: Jeans Cintura Pitillo colores, Clásico, pasador alto BEIGE | C3: Cintura | D3: Pitillo | E3: 25990
A4: 436208 | B4: Jeans Cintura Pitillo colores, Clásico, pasador alto ÓCRE | C4: Cintura | D4: Pitillo | E4: 25990
A5: 436216 | B5: Jeans Cintura Pitillo colores, Clásico, pasador alto VERDE OLIVA | C5: Cintura | D5: Pitillo | E5: 25990
A6: 436248 | B6: Jeans Cintura Pitillo colores, Clásico, pasador alto BURDEO | C6: Cintura | D6: Pitillo | E6: 25991
A7: 436104 | B7: Jeans Cintura Flare, relojero en pretina, pasador trasero en V, CAFÉ | C7: Cintura | D7: Flare | E7: 26990 | F7: EX 4234/ 5 colores | G7: En escritorio
A8: 436106 | B8: Jeans Cintura Flare, relojero en pretina, pasador trasero en V, BEIGE | C8: Cintura | D8: Flare | E8: 26990
A9: 436108 | B9: Jeans Cintura Flare, relojero en pretina, pasador trasero en V, ÓCRE | C9: Cintura | D9: Flare | E9: 26990
A10: 436116 | B10: Jeans Cintura Flare, relojero en pretina, pasador trasero en V, VERDE OLIVA | C10: Cintura | D10: Flare | E10: 26990
A11: 436148 | B11: Jeans Cintura Flare, relojero en pretina, pasador trasero en V, BURDEO | C11: Cintura | D11: Flare | E11: 26990
A12: 437700 | B12: Jeans Cintura Palazzo, gris Acero | C12: Cintura | D12: PALAZZO | E12: 26990 | F12: EX 4249
A13: 437900 | B13: Jeans Gris focalizado | C13: Cintura | D13: PALAZZO | E13: 25990 | F13: EX 4003
A14: 437800 | B14: Jeans Cintura Recto, clásico | C14: Cintura | D14: Recto | E14: 25990 | F14: EX 4248
A15: 436600 | B15: Jeans Clásico cintura Recto, bolsillo ovalado, CAFÉ | C15: Cintura | D15: Recto | E15: 25990
A16: 436600 | B16: Jeans Clásico cintura Recto, bolsillo ovalado, BEIGE | C16: Cintura | D16: Recto | E16: 25990
A17: 436600 | B17: Jeans Clásico cintura Recto, bolsillo ovalado, ÓCRE | C17: Cintura | D17: Recto | E17: 25990
A18: 436600 | B18: Jeans Clásico cintura Recto, bolsillo ovalado, VERDE OLIVA | C18: Cintura | D18: Recto | E18: 25990
A19: 436600 | B19: Jeans Clásico cintura Recto, bolsillo ovalado, BURDEO | C19: Cintura | D19: Recto | E19: 25990
A20: 436600 | B20: Jeans Clásico cintura Recto, bolsillo ovalado | C20: Cintura | D20: Recto | E20: 25990

Sheet Respaldo
A1: 1 | B1: 1 | C1: 2 | D1: 3 | E1: 4 | F1: 5 | G1: 6 | H1: 7 | I1: 8 | J1: 9 | K1: 10 | L1: 11 | M1: 12 | N1: 13 | O1: 14 | P1: 15 | Q1: 16 | R1: 17 | S1: 18 | T1: 19 | U1: 20 | V1: 21 | W1: 22 | X1: 23 | Y1: 24 | Z1: 25 | AA1: 26 | AB1: 27 | AC1: 28
A3: RUT | B3: RUT2 | C3: Razon Social | D3: Ciudad | E3: Direccion | F3: Fono | G3: Vendedor | H3: Correo | I3: WWW | J3: Contacto | K3: Cargo | L3: GRUPO | M3: Credito | N3: Transporte | O3: BLOQUEADO | P3: Dcto | Q3: CONDICION DE PAGO | R3: CELULAR | S3: GIRO | T3: NOMBRE DE TIENDA | U3: COMUNA | V3: Observaciones | W3: Ped_anterior | X3: Cantidad | Y3: Despacho | Z3: Saldo | AA3: % Despacho | AB3: Valor | AC3: Meta Cole-38
A4: 4.878.758-4 | B4: 48787584 | C4: ROBERTO KOBUS PEMSO | D4: ANCUD | E4: PUDETO 143-145 | F4: 998269854 | G4: PATRICIO CUEVAS | H4: tiendasmachos@gmail.com | I4: MACHOS BOUTIQUE@SURNET.CL | J4: JENIFER PAGOS | L4: 4 | M4: 0 | N4: VARMONTT | Q4: CREDITO 30 Y 60 | S4: GRANDES TIENDAS | T4: MACHOS | U4: ANCUD | V4: VARMONTT | X4: 487 | Y4: 432 | Z4: 55 | AA4: 0.88706366 | AB4: 12047130 | AC4: 782
A5: 5.001.562-9 | B5: 50015629 | C5: INES VARGAS PINO | D5: COPIAPO | E5: ATACAMA 461-A | F5: 52-213939 | G5: HECTOR CAFFIERO | J5: INES VARGAS | L5: 3 | M5: 0 | N5: SER VALL | P5: 0.05 | Q5: TRANSF. CONTRA FACTURA | R5: 8-8637797 | S5: TIENDA DE VESTIR | T5: BOUTIQUE GEMINIS | U5: COPIAPO | X5: 0 | Y5: 0 | Z5: 0 | AA5: 0 | AB5: 0 | AC5: 0
A6: 5.384.900-8 | B6: 53849008 | C6: ELIANA RIQUELME R. | D6: FUTRONO | E6: BALMACEDA 249 | F6: 966322618 | G6: PATRICIO CUEVAS | J6: ELIANA RIQUELME | L6: 4 | M6: 0 | N6: TUR BUS | Q6: CREDITO 30 Y 60 | S6: VENTAS | T6: COSAS BOUTIQUE | U6: FUTRONO | X6: 0 | Y6: 0 | Z6: 0 | AA6: 0 | AB6: 0 | AC6: 0
A7: 5.913.365-9 | B7: 59133659 | C7: ANA MARIA MANFREDI CARRASCO | D7: OVALLE | E7: VICUÑA MACKENNA 287 | F7: 053-622626 | G7: HECTOR CAFFIERO | H7: manfredi@hotmail.com | J7: DANIELA O ANA MARIA | K7: DUEÑO | L7: 3 | M7: 0 | N7: CHILE LINDO | Q7: CREDITO 30 Y 60 | S7: VENTAS AL POR MENOR | T7: BOUTIQUE PARA TI | U7: =D7 | X7: 182 | Y7: 116 | Z7: 66 | AA7: 0.63736264 | AB7: 4477180 | AC7: 186.3
A8: 6.031.123-4 | B8: 60311234 | C8: FABIOLA BENAVENTE MEZA | D8: PARRAL | E8: ANIBAL PINTO 590 | F8: 961895384 | G8: CARLOS CUEVAS | H8: tiendaelegance@gmail.com | J8: FABIOLA BENAVENTE | K8: POP DESPACHADO 11/12 | L8: 3 | M8: 0 | N8: VILLA PRAT | Q8: CONTRAFACTURA | S8: BOUTIQUE | T8: ELEGANTE BOUTIQUE | U8: PARRAL | X8: 90 | Y8: 88 | Z8: 2 | AA8: 0.97777778 | AB8: 2223100 | AC8: 51.75
A9: 6.331.910-4 | B9: 63319104 | C9: LUIS SOUMASTRE RAMIREZ | D9: ARICA | E9: 21 DE MAYO 454 | F9: 058-2232959 | G9: HECTOR CAFFIERO | H9: lfsr24@hotmail.com | J9: gloria tapia | L9: 3 | M9: 0 | N9: CHACON | Q9: CREDITO 30 Y 60 | S9: VENTAS AL POR MENOR | U9: ARICA | X9: 0 | Y9: 0 | Z9: 0 | AA9: 0 | AB9: 0 | AC9: 26.45
A10: 6.589.904-3 | B10: 65899043 | C10: ANITA BERTA GADICKE | D10: OSORNO | E10: OHIGGINS 534 | F10: 985067217 | G10: PATRICIO CUEVAS | H10: anitagadicke@gmail.com | J10: ANITA GADICKE | L10: 4 | M10: 0 | N10: CIDHER | Q10: CREDITO 30 Y 60 | S10: BOUTIQUE | T10: ALBANY SPORT | U10: OSORNO | X10: 0 | Y10: 0 | Z10: 0 | AA10: 0 | AB10: 0 | AC10: 0
A11: 6.775.324-0 | B11: 67753240 | C11: MARIA DE LOS ANGELES DIAZ BELLIDO | D11: VILLA ALEMANA | E11: BUENOS AIRE 845 | F11: 32-2951011 | G11: PATRICIO CUEVAS | H11: balaustros2@hotmail.com | I11: BALASUTROSVILLAALEMANA@GMAIL.C | J11: MARIA DE LOS ANGELES | L11: 4 | N11: ABC | Q11: CREDITO 30 Y 60 | S11: BOUTIQUE | T11: BALAUSTROS BOUTIQUE | U11: VILLA ALEMANA | X11: 0 | Y11: 0 | Z11: 0 | AA11: 0 | AB11: 0 | AC11: 0
A12: 6.799.967-3 | B12: 67999673 | C12: ANA MARIA SALVATIERRA TAPIA | D12: CABILDO | E12: HUMERES 727 | F12: 91286053 | G12: CARLOS CUEVAS | H12: anisalta@hotmail.com | J12: ANA MARIA SALVATIERR | L12: 3 | M12: 0 | N12: TUR BUS | Q12: CREDITO 30 Y 60 | S12: BOUTIQUE | T12: BOUTIQUE ANITA | U12: CABILDO | X12: 180 | Y12: 176 | Z12: 4 | AA12: 0.97777778 | AB12: 4426200 | AC12: 216.2
A13: 76.965.431-3 | B13: 769654313 | C13: OPALO VESTUARIO | D13: CONCEPCION | E13: BARROS ARANA 815 LOCAL 14 | F13: 991959818 | G13: PATRICIO CUEVAS | H13: mayobenites@hotmail.com | J13: HILIA CONCHA | K13: DUEÑA | L13: 1 | M13: 0 | N13: CHEVALIER | Q13: CHEQUE 30 DIAS | R13: 99594046 | S13: BOUTIQUE | T13: OPALO BOUTIQUE | U13: CONCEPCION | V13: HIJA MARJORIE BENITEZ, TRANSPORTE CHEVALIER 13/11 | X13: 958 | Y13: 678 | Z13: 280 | AA13: 0.70772443 | AB13: 23822420 | AC13: 635.95
A14: 7.096.837-1 | B14: 70968371 | C14: GLORIA CECILIA OLIVARES TORRES | D14: CHAÑARAL | E14: MERINO JARPA 590 | F14: 09-98175762 | G14: HECTOR CAFFIERO | H14: g.oltorres91@gmail.com | J14: DANIEL CEA COMPRA Y | L14: 1 | M14: 0 | N14: TUR BUS | Q14: CREDITO 30 Y 60 | S14: TIENDA | T14: EVEN EZER | U14: CHAÑARAL | X14: 118 | Y14: 105 | Z14: 13 | AA14: 0.88983051 | AB14: 2900820 | AC14: 143.75
A15: 7.562.033-0 | B15: 75620330 | C15: PATRICIA BARRIA MANCILLA | D15: PORVENIR | E15: JOHN WILLIAMS 034 | F15: 061-2580171 | G15: SERGIO KRAMARENCO | H15: patricia.barria@gmail.com | J15: PATRICIA BARRIA | N15: TRANSCARGO | Q15: CREDITO 30 Y 60 | T15: ROMY'S | U15: PORVENIR | X15: 0 | Y15: 0 | Z15: 0 | AA15: 0 | AB15: 0 | AC15: 0
A16: 7.634.829-4 | B16: 76348294 | C16: CARLOS MELLA ALVARADO | D16: CASTRO | E16: OHIGGINS 658 | F16: 065-2637291 | G16: PATRICIO CUEVAS | H16: tiendamodafiel@gmail.com | J16: SEÑORA SOFIA | L16: 3 | N16: CRUZ DEL SUR | P16: 0 | Q16: CONTRAFACTURA | R16: 9-5791119 | S16: TIENDA Y PAQUETERIA | T16: MODA FIEL | U16: CASTRO | X16: 229 | Y16: 169 | Z16: 60 | AA16: 0.73799127 | AB16: 5766710 | AC16: 248.4
A17: 7.675.412-8 | B17: 76754128 | C17: IRMA ROMERO CASTRO | D17: CURANILAHUE | E17: ARTURO PRAT 1384 | F17: 041/2691287 | G17: PATRICIO CUEVAS | H17: irmafranciscaromero@gmail.com | I17: IRMAFRANCISCAROMERO@GMAIL.COM | J17: IRMA ROMERO | K17: POP DESPACHADO 12/12 | L17: 3 | M17: 0 | N17: CHEVALIER | Q17: CREDITO 30 Y 60 | S17: BOUTIQUE | T17: FRANCISCA ROMERO BOUTIQUE | U17: CURANILAHUE | X17: 0 | Y17: 0 | Z17: 0 | AA17: 0 | AB17: 0 | AC17: 0
A18: 8.259.662-3 | B18: 82596623 | C18: LUIGI ZANDONAI | D18: LA SERENA | E18: BALMACEDA 423 | F18: 51-215122 | G18: HECTOR CAFFIERO | H18: luigizandonay@hotmail.com | J18: LUIGI ZANDONAI | K18: POP DESPACHADO 12/12 | L18: 3 | M18: 0 | N18: PIERO | Q18: CREDITO 30 Y 60 | S18: TIENDA | T18: TIENDA LUIGI ZANDONAI | U18: =D18 | X18: 0 | Y18: 0 | Z18: 0 | AA18: 0 | AB18: 0 | AC18: 48.3
A19: 8.611.778-9 | B19: 86117789 | C19: EMILIA PALMA VILCHES | D19: SAN JAVIER | E19: ARTURO PRAT 2365 | F19: 73-2322862 | G19: CARLOS CUEVAS | H19: mily.palma@gmail.com | J19: MILY PALMA | K19: DUEÑA | L19: 1 | M19: 0 | N19: GEMITA | Q19: CREDITO 30 Y 60 | S19: GRANDES TIENDAS | T19: MILY | U19: SAN JAVIER | V19: SIN INFORMACION COMERCIAL 20/02 | X19: 0 | Y19: 0 | Z19: 0 | AA19: 0 | AB19: 0 | AC19: 0
A20: 8.659.812-4 | B20: 86598124 | C20: RODRIGO EDUARDO SEÑOR LEDESMA | D20: TOME | E20: NOGUEIRA 1137 | F20: 41-2651720 9860610 | G20: PATRICIO CUEVAS | H20: senrodtom@hotmail.com | J20: RODRIGO SEÑOR O MONI | K20: SOCIO | L20: 3 | M20: 0 | N20: VILLA PEAT | Q20: CREDITO 30 Y 60 | S20: VTAS DE PRENDAS DE VESTIR | T20: COMERCIAL LOGROÑO | U20: TOME | V20: SIN INFORMACION COMERCIAL 20/02 | X20: 0 | Y20: 0 | Z20: 0 | AA20: 0 | AB20: 0 | AC20: 0
A21: 8.673.204-1 | B21: 86732041 | C21: ROMAN JUAN CASTRO CAYO | D21: ARICA | E21: AVENIDA 18 DE SEPTIEMBRE 301 L | F21: 58-2232504 | G21: HECTOR CAFFIERO | H21: castro.jade@hotmail.com | J21: ROMAN CASTRO | L21: 1 | M21: 0 | N21: TUR BUS | P21: 0.05 | Q21: CREDITO 30 DIAS | S21: CALZADOS Y ROPAS DE VESTIR | U21: ARICA | X21: 96 | Y21: 73 | Z21: 23 | AA21: 0.76041667 | AB21: 2383040 | AC21: 60.95
A22: 8.780.898-K | B22: 8780898K | C22: PATRICIA HAFON DESMOND | D22: TOCOPILLA | E22: 21 DE MAYO 1549 | F22: 55-812319 | G22: HECTOR CAFFIERO | H22: phafond@hotmail.com | J22: PATRICIA HAFFON | K22: CRISTINA PAGOS | L22: 1 | M22: 0 | N22: RAMOS CHOLELE | Q22: CREDITO 30 Y 60 | S22: BOUTIQUE | U22: =D22 | X22: 0 | Y22: 0 | Z22: 0 | AA22: 0 | AB22: 0 | AC22: 0
A23: 8.837.310-3 | B23: 88373103 | C23: MARIA FRANCISCA IDE SCHMIDT | D23: LA REINA | E23: CARLOS SILVA VILDOSOLA 93 | F23: 2 27586405 | G23: PATRICIO CUEVAS | H23: franciscaides@hotmail.com | J23: SRA FRANCISCA | K23: POP DESPACHADO 11/12 | L23: 3 | M23: 0 | N23: TUR BUS | Q23: CREDITO 30 Y 60 | S23: BOUTIQUE | T23: BOUTIQUE FRANCISCA IDE | U23: LA REINA | X23: 0 | Y23: 0 | Z23: 0 | AA23: 0 | AB23: 0 | AC23: 0
A24: 8.875.220-1 | B24: 88752201 | C24: ANA MARIA CORTES | D24: HUASCO | E24: PEDRO AGUIRRE CERDA 316 | F24: 51-531308 | G24: HECTOR CAFFIERO | H24: cgonza77@hotmail.com | J24: CARLA GONZALEZ | L24: 2 | M24: 0 | N24: TUR BUS | Q24: CREDITO30 DIAS | S24: TIENDA BAZAR Y PAQUETERIA | T24: ANA MARIA BOUTIQUE | U24: =D24 | X24: 0 | Y24: 0 | Z24: 0 | AA24: 0 | AB24: 0 | AC24: 0
A25: 8.990.492-7 | B25: 89904927 | C25: LEYLA DEL CAMPO CASTRO | D25: PUERTO AYSEN | E25: ARTURO PRAT 735 | F25: 067-336824 | G25: SERGIO KRAMARENCO | H25: oleyboutique@gmail.com | J25: LEYLA DEL CAMPO | K25: DUEÑA DE LA TIENDA | L25: 3 | M25: 0 | N25: ATE | Q25: TRANSF. CONTRA ENTREGA | S25: BOUTIQUE | T25: OLEY BOUTIQUE | U25: PUERTO AYSEN | X25: 0 | Y25: 0 | Z25: 0 | AA25: 0 | AB25: 0 | AC25: 0
A26: 9.016.604-2 | B26: 90166042 | C26: RODRIGO SALDIVIA REMOLCOY | D26: QUELLON | E26: LADRILLERO 075 | F26: 65/682901 65/683414 | G26: PATRICIO CUEVAS | H26: lucre_esve1@hotmail.com | J26: LUCRESIA ESCANDON | K26: POP DESPACHADO 12/12 | L26: 4 | M26: 0 | N26: CRUZ DEL SUR | Q26: CREDITO 30 Y 60 | X26: 0 | Y26: 0 | Z26: 0 | AA26: 0 | AB26: 0 | AC26: 0
A27: 9.276.152-5 | B27: 92761525 | C27: CARMEN GLORIA GALLARDO VALERIO | D27: LA UNION | E27: COMERCIO 400 | F27: 64-425041 | G27: PATRICIO CUEVAS | H27: ricardo_lmunoz@yahoo.com | J27: RICARDO MUÑOZ | K27: POP DESPACHADO 12/12 | L27: 3 | M27: 0 | N27: CHEVALIER | Q27: CREDITO 30 Y 60 | S27: TIENDA | T27: PIBAS | U27: LA UNION | X27: 252 | Y27: 179 | Z27: 73 | AA27: 0.71031746 | AB27: 6290480 | AC27: 287.5
A28: 9.305.252-8 | B28: 93052528 | C28: SABINA QUISPE PAIRO | D28: ARICA | E28: 18 SEPTIEMBRE 301 LOCAL 4 | F28: 58-251824 LOCAL | G28: HECTOR CAFFIERO | H28: constanzacontreras1310@gmail.com | J28: SABINA QUISPE | K28: MARLON ZAPATA | L28: 1 | M28: 0 | N28: CHACON | Q28: CREDITO 30 Y 60 | S28: BOUTIQUE | T28: SABY SPORT | U28: ARICA | X28: 196 | Y28: 171 | Z28: 25 | AA28: 0.87244898 | AB28: 4906040 | AC28: 439.3
A29: 9.434.963-K | B29: 9434963K | C29: ROSA EMILIA FUENTES MANCILLA | D29: QUEILEN | E29: PEDRO AGUIRRE CERDA 183 | F29: 65/611209 611543 | G29: PATRICIO CUEVAS | H29: rosa.fuentes.23@gmail.com | J29: ROSA FUENTES MANCILL | K29: VERONICA PAGOS | L29: 3 | M29: 0 | N29: CRUZ DEL SUR | Q29: TRANSF. CONTRA ENTREGA | S29: TIENDA | T29: TIENDA Y PAQUETERIA ROCIO | U29: QUEILEN | X29: 0 | Y29: 0 | Z29: 0 | AA29: 0 | AB29: 0 | AC29: 0
A30: 9.684.131-0 | B30: 96841310 | C30: NEDY BASCUNAN MANSILLA | D30: COYHAIQUE | E30: ERRAZURIZ 261-A | F30: 67-245741 | G30: SERGIO KRAMARENCO | H30: nedybascunan@gmail.com | J30: NEDY | K30: 41619 | L30: 1 | M30: 0 | N30: TRANSMAX | Q30: CONTADO | S30: TIENDA | T30: BOUTIQUE FRANCHESCA | U30: COYHAIQUE | X30: 0 | Y30: 0 | Z30: 0 | AA30: 0 | AB30: 0 | AC30: 345
A31: 9.804.121-4 | B31: 98041214 | C31: MARIA CONCHA CACERES | D31: CONSTITUCION | E31: VIAL 380 A | F31: 71-2673006 | G31: PATRICIO CUEVAS | H31: mariaconcha-63@hotmail.co | J31: MARIA CONCHA CACERES | K31: DUEÑA | L31: 3 | M31: 0 | N31: EMECOL | Q31: CREDITO 30 Y 60 | S31: TIENDA | T31: TRIBAL | U31: CONSTITUCION | X31: 0 | Y31: 0 | Z31: 0 | AA31: 0 | AB31: 0 | AC31: 0
A32: 10.026.410-2 | B32: 100264102 | C32: GLORIA CONTRERAS TORRES | D32: COCHRANNE | E32: RIO COLONIAL 560 | F32: 67-552734 | G32: SERGIO KRAMARENCO | H32: gcontrerastorres@hotmail.cl | J32: GLORIA CONTRERAS | L32: 3 | M32: 0 | N32: ATE | Q32: TRANSF. CONTRA ENTREGA | S32: VENTAS PRENDAS DE VESTIR | U32: COCHRANE | V32: DICOM OK AL 27/2 | X32: 0 | Y32: 0 | Z32: 0 | AA32: 0 | AB32: 0 | AC32: 37.95
A33: 10.270.508-4 | B33: 102705084 | C33: ELIANA VENTURELLI REGLA | D33: CAP. PASTENE | E33: PEDRO MONTT 640 | F33: 84092579 | G33: PATRICIO CUEVAS | H33: elianaventurelliregla@hotmail. | J33: ELIANA VENTURELLI | K33: POP DESPACHADO 12/12 | L33: 3 | M33: 0 | N33: JC | Q33: CHEQUE 30 DIAS | S33: BOUTIQUE | U33: TRAIGUEN | V33: SIN INFORMACION COMERCIAL 20/02 | X33: 64 | Y33: 62 | Z33: 2 | AA33: 0.96875 | AB33: 1573360 | AC33: 36.8
A34: 10.529.776-9 | B34: 105297769 | C34: OLGA OLIVIA POBLETE CONCHA | D34: TRAIGUEN | E34: LAGOS 957 | F34: 950866511 | G34: CARLOS CUEVAS | H34: OLGAPOBLETECONCHA@GMAIL.COM | J34: OLGA POBLETE | L34: 3 | N34: BUSES JC | Q34: TRANSF. CONTRAFACTURA | R34: 0 | S34: BOUTIQUE | T34: FENIX BOUTIQUE | X34: 96 | Y34: 70 | Z34: 26 | AA34: 0.72916667 | AB34: 2423040 | AC34: 70.15
A35: 10.777.684-2 | B35: 107776842 | C35: KETTY ROJAS RAMIREZ | D35: COPIAPO | E35: VILLA DIEGO PORTALES C/11 | F35: 052/241236 | G35: HECTOR CAFFIERO | H35: krojasramirez@gmail.com | L35: 4 | M35: 0 | N35: ENVIAS EXPRESS | Q35: CREDITO 30 Y 60 | S35: TIENDA | X35: 0 | Y35: 0 | Z35: 0 | AA35: 0 | AB35: 0 | AC35: 0
A36: 10.879.819-K | B36: 10879819K | C36: CELIA VASQUEZ BARRERA | D36: VILLARRICA | E36: PEDRO DE VALDIVIA 650 LOCAL 25 | F36: 045-2412431 | G36: PATRICIO CUEVAS | H36: prodigos@live.cl | J36: CELIA VASQUEZ | K36: POP DESPACHADO 11/12 | L36: 1 | M36: 0 | N36: TUR BUS | P36: 0.05 | Q36: CONTADO | T36: PRODIGOS | U36: VILLARRICA | V36: NO CUMPLE PERFIL PARA MOHICANO | X36: 58 | Y36: 56 | Z36: 2 | AA36: 0.96551724 | AB36: 1441420 | AC36: 49.45
A37: 11.354.049-4 | B37: 113540494 | C37: PATRICIA MENA SANDOVAL | D37: TRAIGUEN | E37: AV SAAVEDRA 460 | F37: 045-861873 | G37: PATRICIO CUEVAS | H37: patcemesa@hotmail.com | J37: PATRICIA MENA | L37: 3 | M37: 0 | Q37: CREDITO 30 Y 60 | S37: BOUTIQUE | T37: PATY MENA BOUTIQUE | U37: TRAIGUEN | X37: 0 | Y37: 0 | Z37: 0 | AA37: 0 | AB37: 0 | AC37: 0
A38: 11.407.997-9 | B38: 114079979 | C38: DANITZA OSSES AEDO | D38: TRAIGUEN | E38: CALLE SANTA CRUZ Nº 807 | F38: 45-861192 | G38: PATRICIO CUEVAS | H38: danitzaosses@hotmail.com | J38: DANITZA OSSES | K38: DUEÑA | L38: 3 | M38: 0 | Q38: CREDITO 30 Y 60 | V38: TRANSPORTES JAC , SIN INFORMES COMERCIALES 20/02 | X38: 73 | Y38: 63 | Z38: 10 | AA38: 0.8630137 | AB38: 1798270 | AC38: 50.6
A39: 11.564.359-2 | B39: 115643592 | C39: BELLA FUENTES PINCHEIRA | D39: LINARES | E39: CHACABUCO 435 LOCAL 03 | F39: 73-2219931 | G39: PATRICIO CUEVAS | H39: befupi@gmail.com | J39: BELLA FUENTES | K39: POP DESPACHADO 12/12 | L39: 1 | M39: 0 | N39: CHEVALIER | P39: 0.05 | Q39: CONTADO | R39: 98376422 | S39: BOUTIQUE BAZAR Y PAQUETERIA | T39: D JAVI | U39: LINARES | V39: CANCELA CHEQUE 30 DIAS CON 10% DE DESCUENTO, SU ENCARGADA DE LOCAL ES MINERVA | X39: 480 | Y39: 446 | Z39: 34 | AA39: 0.92916667 | AB39: 11887200 | AC39: 500.25
A40: 11.684.129-0 | B40: 116841290 | C40: HUGO MONTERO FIGUEROA | D40: LOS ANGELES | E40: VALDIVIA 487 LOCAL L | G40: PATRICIO CUEVAS | H40: hugomonterof@yahoo.es | J40: HUGO MONTERO | K40: DUEÑO | L40: 1 | M40: 0 | N40: CHEVALIER | Q40: 30 DIAS | R40: 09-3447832 | S40: TIENDAS | T40: HECHIZOS | U40: LOS ANGELES | V40: TRANSPORTE CHEVALIER | X40: 335 | Y40: 330 | Z40: 5 | AA40: 0.98507463 | AB40: 8369650 | AC40: 385.25
A41: 12.003.736-6 | B41: 120037366 | C41: ARMANDO BARRIA LEGUE | D41: PUERTO NATALES | E41: MANUEL BULNES 731 LOCAL A | F41: 061-413977 | G41: SERGIO KRAMARENCO | H41: tiendarmando@gmial.com | J41: ARMANDO BARRIA | L41: 3 | M41: 0 | N41: TRANSCARGO | Q41: TRANSF. CONTRA ENTREGA | S41: TIENDA | T41: ESPACIO JEANS | U41: PUERTO NATALES | X41: 182 | Y41: 181 | Z41: 1 | AA41: 0.99450549 | AB41: 4475180 | AC41: 218.5
A42: 12.323.239-9 | B42: 123232399 | C42: MABEL ALEJANDRA MUNOZ MOLINER | D42: ANGOL | E42: CAUPOLICAN 341 LOCAL 1 | F42: 45-717973 | G42: PATRICIO CUEVAS | H42: comercialpaucoma@gmail.co | J42: MABEL MUÑOZ | K42: POP RECHAZADO 12/12 | L42: 3 | M42: 0 | N42: TUR BUS | Q42: CONTADO | S42: BOUTIQUE | T42: BOUTIQUE PAULA | U42: ANGOL | V42: SIN INFORMACION COMERCIAL 20/02 | X42: 0 | Y42: 0 | Z42: 0 | AA42: 0 | AB42: 0 | AC42: 0
A43: 12.495.320-0 | B43: 124953200 | C43: RODRIGO BARRENA ARAVENA | D43: MELIPILLA | E43: SERRANO 395 LOCAL 211 | F43: 97491171 | G43: RICHARD CUEVAS | L43: 1 | N43: PROPIO | Q43: CONTADO | R43: 0 | T43: BOUTIQUE CANELA Y MIEL | X43: 0 | Y43: 0 | Z43: 0 | AA43: 0 | AB43: 0 | AC43: 0
A44: 12.838.491-K | B44: 12838491K | C44: JESSICA ARAYA CEPEDA | D44: ANTOFAGASTA | E44: MANUEL RODRIGUEZ 3065 | F44: 9-8640684 | G44: HECTOR CAFFIERO | H44: bebaignacia@hotmail.com | N44: TURBUS | Q44: TRANSF. CONTRA FACTURA | X44: 61 | Y44: 46 | Z44: 15 | AA44: 0.75409836 | AB44: 1505390 | AC44: 60.95
A45: 14.405.243-9 | B45: 144052439 | C45: CECILIA RIVERA ROMERO | D45: TEMUCO | E45: AV. TORREMOLINO 410 LOCAL 132 | F45: 953815405 | G45: PATRICIO CUEVAS | H45: CECILIA.MOHICANO@GMAIL.COM | J45: CECILIA RIVERA | K45: POP DESPACHADO 12/12 | L45: 1 | M45: 0 | N45: CHEVALIER | Q45: 60 - 90 DIAS | R45: 953815405 | S45: BOUTIQUE | T45: RIVERA JEANS | U45: TEMUCO | V45: TUR BUS , SIN INFORMAES COMERCIALES 20/02 | X45: 525 | Y45: 355 | Z45: 170 | AA45: 0.67619048 | AB45: 13305750 | AC45: 608.35
A46: 14.905.682-3 | B46: 149056823 | C46: CLAUDIO TORRES VIERAS | D46: BIO-BIO | E46: DIEGO PORTALES N°1110 | F46: 950089698 | G46: CARLOS CUEVAS | H46: MARGAGONZALEZFLO@GMAIL.COM | J46: MARGARITA | L46: 1 | N46: CHEVALIER | Q46: CONTADO | S46: PAQUETERIA Y PERFUMERIA | T46: EL RINCONCITO DE LA MODA | U46: LOS ALAMOS | X46: 0 | Y46: 0 | Z46: 0 | AA46: 0 | AB46: 0 | AC46: 16.1
A47: 15.627.315-5 | B47: 156273155 | C47: MAURICIO DONOSO MANTOYA | D47: OSORNO | E47: CHOCRANE 651 LOCAL 109 | G47: PATRICIO CUEVAS | H47: mauriciodonosomontoya@hotmail.com | J47: MAURICIO DONOSO | L47: 1 | N47: TUR BUS OFICINA | P47: 0 | Q47: CREDITO 30 Y 60 | R47: 77999446 | S47: BOUTIQUE | T47: BOUTIQUE HERRADURA | U47: OSORNO | X47: 0 | Y47: 0 | Z47: 0 | AA47: 0 | AB47: 0 | AC47: 0
A48: 15.814.934-6 | B48: 158149346 | C48: CAROLINA DELGADO ROMERO | D48: LA LIGUA | E48: DENEBOLA 1033 | G48: CARLOS CUEVAS | Q48: CONTADO | R48: 0 | X48: 0 | Y48: 0 | Z48: 0 | AA48: 0 | AB48: 0 | AC48: 0
A49: 16.065.905-K | B49: 16065905K | C49: PATRICIA CANALES | D49: PUNTA ARENAS | E49: BORIES 932 LOCAL 201 | F49: 09-94044305 | G49: SERGIO KRAMARENCO | H49: jorgecabett@hotmail.com | J49: NARIA OYARZUN LEIVA | L49: 3 | N49: TRANSCARGO | Q49: TRANSF. CONTRA ENTREGA | R49: 09-94044305 / 61-710598 | S49: TIENDA | T49: TIENDA JORGE CABBET | U49: PUNTA ARENAS | X49: 80 | Y49: 22 | Z49: 58 | AA49: 0.275 | AB49: 2010200 | AC49: 124.2
A50: 16.868.500-9 | B50: 168685009 | C50: FRANKA SALAZAR MUÑOZ | D50: ANTOFAGASTA | E50: AV LLANQUIHUE 4216 D13 | F50: 055-547656 | G50: HECTOR CAFFIERO | H50: franka92@hotmail.com | J50: FRANKA SALAZAR | L50: 1 | M50: 0 | N50: TUR BUS | Q50: CREDITO 30 Y 60 | R50: 9-1595286 | S50: BOUTIQUE | T50: BOUTIQUE FRANKAS | U50: ANTOFAGASTA | V50: BLOQUEO PEDIDO X CLIENTE NO DESPACHAR FALTA FONDOS | X50: 0 | Y50: 0 | Z50: 0 | AA50: 0 | AB50: 0 | AC50: 0
A51: 18.282.453-4 | B51: 182824534 | C51: CONSTANZA CANALES OYARZUN | D51: PUNTA ARENAS | E51: BORIES 932 LOCAL 204 | F51: 61-710598 | G51: SERGIO KRAMARENCO | H51: jorgecabett@hotmail.com | J51: MARIA OYARZUN | L51: 3 | M51: 0 | N51: TRANSCARGO | Q51: CREDITO 30 Y 60 | S51: TIENDA | T51: TIENDAS JORGE CABETT | U51: PUNTA ARENAS | X51: 0 | Y51: 0 | Z51: 0 | AA51: 0 | AB51: 0 | AC51: 0
A52: 3.877.646-0 | B52: 38776460 | C52: LUIS CARRASCO PERALTA | D52: SAN FERNANDO | E52: CHILLAN 502 LOCAL 13 | F52: 942948977 | G52: PATRICIO CUEVAS | H52: KATTIE.CARRASCO@HOTMAIL.COM | L52: 1 | N52: ANDIMAR | Q52: CONTADO | R52: 0 | T52: TIENDAS DE VESTIR Y CALZADO | U52: SAN FERNANDO | X52: 0 | Y52: 0 | Z52: 0 | AA52: 0 | AB52: 0 | AC52: 0
A53: 52.004.390-K | B53: 52004390K | C53: WILFREDO ROJAS QUILODR | D53: SAN CARLOS | E53: BALMACEDA 315 | F53: 42-411798 | G53: PATRICIO CUEVAS | H53: ALBANYSPORT@GMAIL.COM | L53: 3 | N53: CHEVALIER | Q53: CONTRAFACTURA | X53: 77 | Y53: 65 | Z53: 12 | AA53: 0.84415584 | AB53: 1891230 | AC53: 115
A54: 7.295.293-6 | B54: 72952936 | C54: ANA SAAVEDRA ORTIZ | D54: CAÑETE | E54: COVADONGA 240 LOCAL 1 | F54: 41-2-611782 | G54: PATRICIO CUEVAS | H54: ANASAAVEDRAO@HOTMAIL.COM | J54: ANA SAAVEDRA | N54: CHEVALIER | Q54: CREDITO 30 Y 60 | V54: TRANSPORTE CHEVALIER , SIN INFORMES COMERCIALES 20/02 | X54: 66 | Y54: 47 | Z54: 19 | AA54: 0.71212121 | AB54: 1651340 | AC54: 117.3
A55: 7.509.921-5 | B55: 75099215 | C55: NOLBERTO AVILA CORTES | D55: CAUQUENES | E55: PRAT 549 | F55: 976689778 | G55: PATRICIO CUEVAS | H55: NOLBERTO.E.AVLA@GMAIL.COM | J55: SRA. CECILIA | K55: DUEÑA | L55: 1 | N55: VILLA PRAT | Q55: CONTADO | R55: 0 | T55: SCARLETT BOUTIQUE | U55: CAUQUENES | X55: 297 | Y55: 207 | Z55: 90 | AA55: 0.6969697 | AB55: 7334030 | AC55: 181.7
A56: 70.002.640-K | B56: 70002640K | C56: COOPPATRIA | D56: SANTIAGO | E56: ZENTENO 190 | F56: 02-26994660 | G56: PATRICIO CUEVAS | H56: pcaceres@coopatria.cl | J56: PAOLA CACERES | K56: PAOLA SAN MARTIN | L56: 1 | M56: 0 | Q56: CREDITO 30 Y 60 | X56: 0 | Y56: 0 | Z56: 0 | AA56: 0 | AB56: 0 | AC56: 0
A57: 76.007.823-9 | B57: 760078239 | C57: COMERCIAL CARMEN TEMER EIRL | D57: ARAUCO | E57: ESMERALDA 365 | F57: 041-2552402 | G57: PATRICIO CUEVAS | H57: carmentemer@gmail.com | J57: CARMEN TEMER | K57: POP DESPACHADO 11/12 | L57: 3 | M57: 0 | N57: CHEVALIER | Q57: CREDITO 30 Y 60 | S57: PRENDAS DE VESTIR | T57: MULTITIENDAS TEMER | U57: ARAUCO | X57: 0 | Y57: 0 | Z57: 0 | AA57: 0 | AB57: 0 | AC57: 0
A58: 76.013.196-2 | B58: 760131962 | C58: MARIA PILAR JEREZ Y CIA.LTDA. | D58: ANGOL | E58: JULIO SEPULVEDA 331 | F58: 45-712538 | G58: PATRICIO CUEVAS | H58: boutiqueloscisnes@gmail.com | J58: SRA PILAR JEREZ | K58: POP DESPACHADO 12/12 | L58: 3 | M58: 0 | N58: GEMITA | Q58: CONTADO | S58: BOUTIQUE | U58: ANGOL | X58: 27 | Y58: 22 | Z58: 5 | AA58: 0.81481481 | AB58: 656730 | AC58: 44.85
A59: 76.017.630-3 | B59: 760176303 | C59: COMERCIAL Q & M LTDA. | D59: QUELLON | E59: LADRILLEROS 247 | F59: 065-292000 | G59: PATRICIO CUEVAS | H59: malvarez@dimarsa.cl | J59: MIRIAM ALVAREZ COMPR | K59: POP DESPACHADO 12/12 | L59: 1 | M59: 0 | N59: SANCHEZ | P59: 0.05 | Q59: 6O DIAS | S59: GRANDES TIENDAS | T59: DIMARSA | U59: QUELLON | V59: TRANSPORTE SANCHEZ | X59: 0 | Y59: 0 | Z59: 0 | AA59: 0 | AB59: 0 | AC59: 0
A60: 76.017.630-3 | B60: 760176303 | C60: COMERCIAL Q&MPUERTO VARAS | D60: PUERTO VARAS | E60: SALVADOR 117 | F60: 065-2292650 | G60: PATRICIO CUEVAS | H60: svargas@dimarsa.cl | J60: SANDRA VARGAS | K60: JEFA DE COMPRAS | L60: 2 | N60: SANCHEZ | Q60: 60 DIAS | S60: GRANDES TIENDAS | T60: DIMARSA | U60: PUERTO VARAS | X60: 0 | Y60: 0 | Z60: 0 | AA60: 0 | AB60: 0 | AC60: 0
A61: 76.048.404-0 | B61: 760484040 | C61: SOC.COM.DON JORGE LTDA | D61: PANGUIPULLI | E61: MARTINEZ DE ROZAS 728 | F61: 063-311014-311089 | G61: PATRICIO CUEVAS | H61: jorgeflandezg@yahoo.com | J61: ALEJANDRA FLANDEZ | L61: 3 | M61: 0 | N61: TALADRIZ CARGO | Q61: 30 DIAS | R61: 88668259 | S61: COMERCIALIZADORA DE VESTUARIO | T61: DON JORGE | U61: PANGUIPULLI | V61: TRANSPORTE LA FRONTERA , SIN INFORMACION COMERCIAL 20/02 | X61: 0 | Y61: 0 | Z61: 0 | AA61: 0 | AB61: 0 | AC61: 6.9
A62: 76.049.842-4 | B62: 760498424 | C62: INVERSIONES JULIAN LTDA. | D62: RENGO | E62: PRAT 325 | F62: 09-72950801 | G62: PATRICIO CUEVAS | H62: fernanda.roman@san-antonio.cl | J62: FERNANDA ROMAN | L62: 2 | M62: 0 | N62: JOKADAL | P62: 0.05 | Q62: 45 dias | S62: GRANDES TIENDAS | T62: MULTITIENDAS SAN ANTONIO | U62: RENGO | X62: 998 | Y62: 942 | Z62: 56 | AA62: 0.94388778 | AB62: 25008020 | AC62: 637.1
A63: 76.067.887-2 | B63: 760678872 | C63: SOC COM SAN MARTIN Y TORRES LTDA | D63: SAN CARLOS | E63: SERRANO 544 LOCAL 1-2 | F63: 042-416759 | G63: PATRICIO CUEVAS | H63: jsanmartin@tiendaelpunto.cl | L63: 3 | M63: 0 | N63: GEMITA | Q63: CREDITO 30 Y 60 | S63: BOUTIQUE | U63: =D63 | X63: 0 | Y63: 0 | Z63: 0 | AA63: 0 | AB63: 0 | AC63: 0
A64: 76.072.224-3 | B64: 760722243 | C64: SOC.COMERCIAL BOBERC LTDA. | D64: CASTRO | E64: BLANCO 169 | F64: 65-3337952 | G64: PATRICIO CUEVAS | H64: boberck ptomontt@123.cl | K64: POP DESPACHADO 12/12 | L64: 3 | M64: 0 | Q64: CREDITO 30 Y 60 | S64: GRANDES TIENDAS | U64: CASTRO | X64: 0 | Y64: 0 | Z64: 0 | AA64: 0 | AB64: 0 | AC64: 0
A65: 76.078.517-2 | B65: 760785172 | C65: DON CRISTOBAL LTDA. | D65: LA UNION | E65: ANGAMOS 520 | F65: 064-2426901 | G65: PATRICIO CUEVAS | H65: valentinaboutique01@gmail.com | J65: DORIS SALGADO | K65: DUEÑA | N65: ECOEXX | Q65: CREDITO 30 Y 60 | R65: 98248393 | S65: BOUTIQUE | T65: VALENTINA BOUTIQUE | U65: LA UNION | X65: 0 | Y65: 0 | Z65: 0 | AA65: 0 | AB65: 0 | AC65: 0
A66: 76.079.186-5 | B66: 760791865 | C66: CARMEN WILLIAMS RIVERA EIRL | D66: PUERTO AYSEN | E66: SARGENTO ALDEA 1160 | F66: 67-336452 | G66: SERGIO KRAMARENCO | H66: tiendajavbian@gmail.com | J66: Jorge QUINTANA | L66: 3 | N66: ATE | Q66: TRANSF. CONTRA ENTREGA | R66: 9-0507606 | V66: TRANSPORT ATE | X66: 70 | Y66: 34 | Z66: 36 | AA66: 0.48571429 | AB66: 1749300 | AC66: 95.45
A67: 76.090.949-1 | B67: 760909491 | C67: SOCIEDAD COMERCIAL OLGA BOUTIQUE LTDA | D67: VILLARRICA | E67: CAMILO HENRIQUEZ 331-B | F67: 45-416539 | G67: PATRICIO CUEVAS | H67: olguitahermosilla@hotmail.com | J67: OLGA HERMOSILLA | N67: TUR BUS | Q67: CREDITO 30 Y 60 | S67: BOUTIQUE | T67: OLGA BOUTIQUE | U67: VILLARICA | X67: 0 | Y67: 0 | Z67: 0 | AA67: 0 | AB67: 0 | AC67: 0
A68: 76.099.347-6 | B68: 760993476 | C68: GLADYS VALDIVIA PEREZ EIRL | D68: LA LIGUA | E68: URIBE 166 LOCAL 2 | F68: 989226623 | G68: CARLOS CUEVAS | H68: avenuelaligua@gmail.com | J68: GLADYS VALDIVIA | K68: SOCIAS | L68: 1 | M68: 0 | N68: JT | Q68: CONTADO | S68: BOUTIQUE | T68: BOUTIQUE AVENUE | U68: LA LIGUA | X68: 69 | Y68: 31 | Z68: 38 | AA68: 0.44927536 | AB68: 1697310 | AC68: 70.15
A69: 76.121.220-6 | B69: 761212206 | C69: SOC.COM.INOSTROZA GOMEZ LTDA. | D69: COYHAIQUE | E69: PRAT 577 | F69: 67-215040 | G69: SERGIO KRAMARENCO | H69: tiendayuly@patagoniachile.cl | J69: PATRICIA GOMEZ | L69: 3 | M69: 0 | N69: FIORDOS | Q69: TRANSF. CONTRA ENTREGA | R69: 984797337 | S69: GRANDES TIENDAS | T69: TIENDAS YULY | U69: COYHAIQUE | X69: 144 | Y69: 109 | Z69: 35 | AA69: 0.75694444 | AB69: 3544560 | AC69: 179.4
A70: 76.168.779-4 | B70: 761687794 | C70: SOCIEDAD COMERCIAL C'MUA LTDA | D70: SANTA CRUZ | E70: RAFAEL CASANOVA 132 A | F70: 72-824563 | G70: RICHARD CUEVAS | H70: tiendacmua@gmail.com | L70: 3 | N70: ANDIMAR | Q70: CONTRAENTREGA | X70: 87 | Y70: 64 | Z70: 23 | AA70: 0.73563218 | AB70: 2190130 | AC70: 173.65
A71: 76.183.909-8 | B71: 761839098 | C71: SOCIEDAD COMERCIAL MKD CLOTHING LIMIT | D71: SANTIAGO | E71: BADAJOZ 100 OFICINA 824 | F71: 2297995 - 02-3423289 | G71: RICHARD CUEVAS | H71: cvegamartino@gmail.com | J71: CARLOS VEGA | K71: POP DESPACHADO 11/12 | L71: 4 | M71: 0 | N71: RETIRA | Q71: CREDITO 30 Y 60 | R71: 9-6459506 | S71: COMPRA VENTA PRENDAS DE VESTIR | T71: MKD LONDON CLOTHIN | U71: LAS CONDES | V71: RETIRAN AVISAR A CARLOS VEGA , SIN INFORMACION COMERCIAL 20/02 | X71: 456 | Y71: 386 | Z71: 70 | AA71: 0.84649123 | AB71: 11392440 | AC71: 289.8
A72: 76.195.255-2 | B72: 761952552 | C72: COMERCIAL NACE SPA | D72: CASTRO | E72: SAN MARTIN 539 | F72: 961418070 | G72: PATRICIO CUEVAS | H72: e.anabalon@mawi.cl, n.anabalon@mawi.cl, VENTAS@MAWI.CL | J72: ERIKA ANABALON | N72: ECOEXX | P72: 0.05 | Q72: 60DIAS | S72: GRANDES TIENDAS | T72: MAWI | U72: CASTRO | X72: 320 | Y72: 248 | Z72: 72 | AA72: 0.775 | AB72: 8069800 | AC72: 533.6
A73: 76.198.195-1 | B73: 761981951 | C73: COMERCIALIZADORA FACHAS Y CIA LTDA | D73: LA LIGUA | E73: ORTIZ DE ROZAS 431 | F73: 33-2713347 | G73: RICHARD CUEVAS | H73: fachasltda@hotmail.com | J73: MARIA TERESA NAVARRO | K73: POP DESPACHADO 11/12 | L73: 3 | M73: 0 | N73: TUR BUS | Q73: CREDITO 30 Y 60 | S73: VESTUARIO Y ART DE HOGAR | U73: LA LIGUA | X73: 44 | Y73: 30 | Z73: 14 | AA73: 0.68181818 | AB73: 1089560 | AC73: 72.45
A74: 76.259.929-5 | B74: 762599295 | C74: VIOLETA LILIANA MEZA FLORES E.I.R.L. | D74: IQUIQUE | E74: VIVAR 916 | F74: 057-2391306 | G74: HECTOR CAFFIERO | H74: LILIANAMEZA@LIVE.COM | N74: Pullman Cargo | Q74: CREDITO 30 Y 60 | X74: 0 | Y74: 0 | Z74: 0 | AA74: 0 | AB74: 0 | AC74: 0
A75: 76.339.520-0 | B75: 763395200 | C75: CONFECCIONES ARAUCO EIRL | D75: ARAUCO | E75: CONDELL 310 | F75: 412553099 | G75: PATRICIO CUEVAS | H75: tiendascycecilia@gmail.com | J75: CECILIA | L75: 4 | M75: 0 | N75: VILLA PRAT | Q75: CREDITO 30 Y 60 | S75: CONFECCIONES Y COMERZIALISACION | T75: C Y CECILIA | U75: ARAUCO | V75: TRANSPORTE VILLA PRAT , SIN INFORMACION COMERCIAL 20/02 | X75: 98 | Y75: 80 | Z75: 18 | AA75: 0.81632653 | AB75: 2421020 | AC75: 170.2
A76: 76.368.393-1 | B76: 763683931 | C76: VIRGINIA DIAZ E HIJOS LTDA. | D76: ANGOL | E76: LAUTARO 362 2PISO | F76: 45-713425 | G76: PATRICIO CUEVAS | H76: alfredonazal@gmail.com | J76: ALFREDO NAZAL | K76: DUEÑA | L76: 3 | M76: 0 | N76: GEMITA | Q76: CREDITO 30 Y 60 | S76: TIENDA | T76: SULU | X76: 0 | Y76: 0 | Z76: 0 | AA76: 0 | AB76: 0 | AC76: 0
A77: 76.454.354-8 | B77: 764543548 | C77: TIENDAS ALFREDO NAZAL EIRL | D77: ANGOL | E77: LAUTARO # 401 | F77: 998842676 | G77: PATRICIO CUEVAS | H77: ALFREDO NAZAL@GMAIL.COM | L77: 1 | M77: 0 | N77: GEMITA | Q77: CONTADO | S77: VENTA PRENDAS DE VESTIR | T77: COM RAIMUNDO | U77: =D77 | X77: 120 | Y77: 117 | Z77: 3 | AA77: 0.975 | AB77: 2986800 | AC77: 164.45
A78: 76.511.829-8 | B78: 765118298 | C78: GRANDES TIENDAS CASA BROWN SPA | D78: CASTRO | E78: THOMPSON 278 | F78: 065-530546 | G78: PATRICIO CUEVAS | H78: casabrown@live.cl | J78: MARCELA | L78: 1 | M78: 0 | N78: VARMONTT | Q78: CREDITO 30 Y 60 | R78: 85874622 | S78: TIENDA | T78: CASA BROWN | U78: CASTRO | X78: 187 | Y78: 138 | Z78: 49 | AA78: 0.73796791 | AB78: 4643130 | AC78: 218.5
A79: 76.658.950-2 | B79: 766589502 | C79: COOPELAN COMERCIAL S.A | D79: LOS ANGELES | G79: PATRICIO CUEVAS | N79: GEMITA | Q79: CREDITO 30 Y 60 | R79: 0 | X79: 376 | Y79: 194 | Z79: 182 | AA79: 0.51595745 | AB79: 9414240 | AC79: 216.2
A80: 76.662.352-2 | B80: 766623522 | C80: ARTICULOS ELECTRONICOS NATALIA SAEZ MENDEZ E.I.R.L | D80: CHILLAN | E80: CONSTITUCION 810 LOCAL 6 | F80: 950150910 | G80: PATRICIO CUEVAS | H80: enrique.pablo.c@gmail.com | J80: NATALIA SAENZ | L80: 1 | M80: 0 | N80: CHEVALIER | Q80: 60-90 DIAS | R80: 950150910 | S80: VENTA DE PRENDAS DE VESTIR | T80: BONITA BOUTIQUE | U80: CHILLAN | V80: TRANSPORTES CHEVALIER , SIN INFORME COMERCIAL 20/02 | X80: 1231 | Y80: 897 | Z80: 334 | AA80: 0.72867587 | AB80: 30927690 | AC80: 1059.15
A81: 76.687.183-6 | B81: 766871836 | C81: NOELIA BOUTIQUE | D81: LINARES | E81: BRAZIL PORTAL ESTACION 479 LOC. 32 | F81: 987952316 | G81: RICHARD CUEVAS | H81: NOELIAGARRIDO33@GMAIL.COM | J81: NOELIA GARRIDO | K81: DUEÑA | L81: 1 | N81: CHEVALIER | Q81: 30-60 DIAS | R81: 0 | S81: BOUTIQUE | T81: NOELIA BOUTIQUE | U81: LINARES | X81: 750 | Y81: 76 | Z81: 674 | AA81: 0.10133333 | AB81: 18448500 | AC81: 842.95
A82: 76.821.717-3 | B82: 768217173 | C82: COMERCIAL Y SERVICIOS WOLLERMANN SPA | D82: PUERTO MONTT | G82: PATRICIO CUEVAS | Q82: CONTADO | R82: 0 | X82: 0 | Y82: 0 | Z82: 0 | AA82: 0 | AB82: 0 | AC82: 0
A83: 76.865.111-6 | B83: 768651116 | C83: SABA Y MILADE LTDA | D83: CURANILAHUE | E83: CAUPOLICAN 733 | F83: 940127841 | G83: CARLOS CUEVAS | H83: SABAYMILADE@GMAIL.COM | J83: CALUDIA METUAZE | L83: 3 | N83: CHEVALIER | Q83: TRANSF. CONTRA FACTURA | R83: 0 | X83: 0 | Y83: 0 | Z83: 0 | AA83: 0 | AB83: 0 | AC83: 0
A84: 77.029.510-6 | B84: 770295106 | C84: SIEGMUND HNOS.LTDA. | D84: VICTORIA | E84: PISAGUA 1201 | F84: 98659430 | G84: PATRICIO CUEVAS | H84: paulafsiegmunds@gmail.com | J84: PAULA SIEGMUND | K84: PATRICIA PAGOS | L84: 1 | M84: 0 | N84: PALMA | Q84: CREDITO 30 Y 60 | S84: GRANDES TIENDAS | T84: CASA SIEGMUND | U84: VICTORIA | V84: GEMITA | X84: 48 | Y84: 46 | Z84: 2 | AA84: 0.95833333 | AB84: 1187520 | AC84: 47.15
A85: 77.030.130-0 | B85: 770301300 | C85: DOLLY S.A. | D85: PUERTO MONTT | E85: URMENETA #292 | F85: 65-2257585 | G85: PATRICIO CUEVAS | H85: proveedores.adulto@dolly.cl | J85: ZUCETTE | K85: POP DESPACHADO 12/12 | L85: 1 | M85: 0 | N85: VARMONTT | P85: 0.05 | Q85: 30DIAS | S85: GRANDES TIENDAS | T85: DOLLY | U85: PUERTO MONTT | V85: CLIENTE CANCELA CON CHEQUE 30 DIAS 10% DESCUENTOVARMONTT | X85: 607 | Y85: 565 | Z85: 42 | AA85: 0.93080725 | AB85: 15074940 | AC85: 691.15
A86: 77.143.280-8 | B86: 771432808 | C86: SOC.COM.JORGE ANANIAS | D86: MULCHEN | E86: VILLAGRAN 580 | F86: 998864093 | G86: CARLOS CUEVAS | H86: PILAR_ANANIAS@HOTMAIL.COM | J86: PILAR ANANIAS | K86: DUEÑA | L86: 4 | M86: 0 | N86: CHEVALIER | Q86: CREDITO30 Y 60 | S86: GRANDES TIENDAS | T86: CASA REAL | U86: MULCHEN | X86: 143 | Y86: 112 | Z86: 31 | AA86: 0.78321678 | AB86: 3547570 | AC86: 156.4
A87: 77.326.810-K | B87: 77326810K | C87: GONART MODA LTDA. | D87: OVALLE | E87: BENAVENTE 75 | F87: 053/2625600 | G87: HECTOR CAFFIERO | H87: gonartmodas@gmail.com | N87: CHILE LINDO | Q87: CREDITO 30 Y 60 | S87: MULTITIENDA VESTUARIO | T87: GONART | U87: OVALLE | X87: 83 | Y87: 69 | Z87: 14 | AA87: 0.8313253 | AB87: 2050170 | AC87: 115
A88: 77.359.210-1 | B88: 773592101 | C88: DICAS LTDA. | D88: CASTRO | E88: SAN MARTIN 409 | F88: 065-292650 | G88: PATRICIO CUEVAS | H88: svargas@dimarsa.cl | J88: SANDRA VARGAS | K88: POP DESPACHADO 12/12 | L88: 1 | M88: 0 | N88: SANCHEZ | Q88: 60DIAS | S88: GRANDES TIENDAS | T88: DIMARSA | U88: CASTRO | V88: TRANSPORTE SANCHEZ | X88: 0 | Y88: 0 | Z88: 0 | AA88: 0 | AB88: 0 | AC88: 0
A89: 77.570.460-8 | B89: 775704608 | C89: COMERCIAL REGINA LTDA | D89: SANTIAGO | E89: PADRE ORELLANA 1437 | G89: PATRICIO CUEVAS | H89: AURELIO.HUILCA27@HOTMAIL.COM | L89: 4 | N89: PROPIO | Q89: CREDITO 30 Y 60 | R89: 0 | X89: 0 | Y89: 0 | Z89: 0 | AA89: 0 | AB89: 0 | AC89: 0
A90: 77.576.530-5 | B90: 775765305 | C90: ALMACENES ELTIT LTDA | D90: PUCON | E90: OHIGGINS 292 | F90: 45-441103-379550 | G90: PATRICIO CUEVAS | J90: IVONNE OSORIO | L90: 1 | M90: 0 | N90: PROPIO | Q90: CONTADO | S90: GRANDES TIENDAS | T90: ELTIT | U90: PUCON | V90: TRANSPORTE PROPIOP | X90: 0 | Y90: 0 | Z90: 0 | AA90: 0 | AB90: 0 | AC90: 0
A91: 77.594.510-9 | B91: 775945109 | C91: SOC.MATURANA GALVAN Y CIA.LTDA. | D91: COPIAPO | E91: ATACAMA 541 L-E | F91: 052-236479 | G91: HECTOR CAFFIERO | J91: TULIO MATURANA | K91: POP DESPACHADO 12/12 | L91: 1 | M91: 0 | N91: EXPRESS | Q91: CREDITO 30 Y 60 | S91: BOUTIQUE | T91: BOUTIQUE PILCHAS | U91: =D91 | X91: 0 | Y91: 0 | Z91: 0 | AA91: 0 | AB91: 0 | AC91: 8.05
A92: 77.934.770-2 | B92: 779347702 | C92: SEÑOR LEDESMA HNOS. LTDA. | D92: TOME | E92: MANUEL MONTT 1198 | F92: 041-2650083 | G92: PATRICIO CUEVAS | H92: juansenor@vtr.net | J92: JUAN SEÑOR LEDESMA | K92: POP DESPACHADO 12/12 | L92: 3 | M92: 0 | N92: VILLA PRAT | Q92: CREDITO 30 Y 60 | S92: ART DEPORTIVO | T92: COMERCIAL SEVILLA | U92: TOME | X92: 0 | Y92: 0 | Z92: 0 | AA92: 0 | AB92: 0 | AC92: 0
A93: 78.416.190-0 | B93: 784161900 | C93: SOC.COMERCIAL BUVINIC LTDA. | D93: PUNTA ARENAS | E93: BORIES 766 | F93: 996407930 | G93: SERGIO KRAMARENCO | H93: ALEBUVINIC@GLOBALCOM.CL | I93: bingojeanspuq@hotmail.com | L93: 1 | N93: TRANSCARGO | Q93: TRANSF. CONTRA ENTREGA | R93: 9-96407930 | S93: TIENDA BAZAR | T93: BINGO JEANS | U93: PUNTA ARENAS | X93: 260 | Y93: 225 | Z93: 35 | AA93: 0.86538462 | AB93: 6417400 | AC93: 441.6
A94: 78.801.490-2 | B94: 788014902 | C94: ALBASINI E HIJOS LIMITADA | D94: COPIAPO | E94: O'HIGGINS Nø402-420 | F94: 52-212788 | G94: HECTOR CAFFIERO | H94: franca@albasini.cl | J94: FRANCA ALBASINI | L94: 1 | M94: 0 | N94: Van Oosterwyk | Q94: CREDITO 30 Y 60 | S94: GRANDES TIENDAS | T94: ALBASINI SPORT | U94: =D94 | X94: 151 | Y94: 138 | Z94: 13 | AA94: 0.91390728 | AB94: 3729490 | AC94: 162.15
A95: 78.840.090-K | B95: 78840090K | C95: BOUTIQUE ADIQTUS LTDA. | D95: OSORNO | E95: RAMIREZ 977 LOCAL 29 | F95: 64-201105 | G95: PATRICIO CUEVAS | H95: bveram@hotmail.com | J95: BLANCA VERA | K95: POP DESPACHADO 12/12 | L95: 2 | M95: 0 | N95: TUR BUS | Q95: 30 DÍAS | S95: BOUTIQUE | T95: BOUTIQUE ADIQTUS | U95: OSORNO | X95: 133 | Y95: 118 | Z95: 15 | AA95: 0.88721805 | AB95: 3325670 | AC95: 188.6
A96: 79.827.960-2 | B96: 798279602 | C96: COMERCIAL LOS CARRERA LTDA | D96: COQUIMBO | E96: ALDUNATE 1138 | F96: 51-315989 | G96: HECTOR CAFFIERO | H96: sin email | J96: SRTA ISABEL | L96: 3 | M96: 0 | N96: CHILE LINDO | Q96: CREDITO 30 Y 60 | S96: BOUTIQUE | T96: BOUTIQUE TEENS | U96: =D96 | X96: 0 | Y96: 0 | Z96: 0 | AA96: 0 | AB96: 0 | AC96: 0
A97: 79.862.960-3 | B97: 798629603 | C97: EL ARTE DE VESTIR S.A. | D97: PUNTA ARENAS | E97: ERRAZURIZ 644 | F97: 615320-615350-615370 | G97: SERGIO KRAMARENCO | H97: jaguila@elartedevestir.cl | J97: RODRIGO ALVAREZ | K97: POP DESPACHADO 11/12 | L97: 3 | M97: 0 | N97: CONOSUR | Q97: TRANSF. CONTRA ENTREGA | R97: 972386296 | S97: GRANDES TIENDAS, CALZADO, IMP | T97: EL ARTE DE VESTIR | U97: PUNTA ARENAS | X97: 430 | Y97: 416 | Z97: 14 | AA97: 0.96744186 | AB97: 10335700 | AC97: 557.75
A98: 79.982.490-6 | B98: 799824906 | C98: COMERCIAL MULTICENTRO LTDA. | D98: TALCA | E98: AV 07 ORIENTE 1620 | F98: 71-214581 | G98: RICHARD CUEVAS | H98: MARCELOC@MULTICENTRO.CL | K98: POP DESPACHADO 12/12 | L98: 2 | M98: 0 | N98: PROPIO | Q98: CREDITO 60 DIAS | T98: MULTICENTRO | U98: TALCA | X98: 2550 | Y98: 2487 | Z98: 63 | AA98: 0.97529412 | AB98: 62313500 | AC98: 2889.95
A99: 81.210.300-8 | B99: 812103008 | C99: JAVER HNOS Y CIA LTDA | D99: SAN ANTONIO | E99: CENTENARIO 105 | F99: 962479655 | G99: RICHARD CUEVAS | H99: M.ARMIJO@JAVER.CL | I99: M.ARMIJO@JAVER.CL | J99: M ARMIJO VENTAS | L99: 2 | M99: 0 | N99: BEZANILLA | P99: 5 | Q99: 30 DÍAS | S99: GRANDES TIENDAS | T99: JAVER | U99: =D99 | X99: 144 | Y99: 116 | Z99: 28 | AA99: 0.80555556 | AB99: 3562560 | AC99: 173.65
A100: 81.242.500-5 | B100: 812425005 | C100: COOPERCARAB LTDA | D100: ANTOFAGASTA | E100: MAIPU 667 | F100: (55)280856 | G100: PATRICIO CUEVAS | H100: tesoreriaantofa@coopercarabc.c | L100: 2 | M100: 0 | N100: PROPIO | P100: 0.05 | Q100: 60DIAS | S100: GRANDES TIENDAS | T100: COOPERCARAB | U100: ANTOFAGASTA | X100: 758 | Y100: 284 | Z100: 474 | AA100: 0.37467018 | AB100: 18103342 | AC100: 1179.9
A101: 81.242.500-5 | B101: 812425005 | C101: COOPERCARAB LTDA | D101: CONCEPCION | E101: BERNANDO O'HIGGINS 80 | F101: (41) 2521576 | G101: PATRICIO CUEVAS | H101: comprasmktconcep@coopercarab.c | L101: 2 | M101: 0 | N101: PROPIO | P101: 0.05 | Q101: 60DIAS | S101: GRANDES TIENDAS | T101: COOPERCARAB | U101: CONCEPCION | X101: 758 | Y101: 284 | Z101: 474 | AA101: 0.37467018 | AB101: 18103342 | AC101: 1179.9
...

Sheet BASE DE DATOS OFICIAL
A1: 1 | B1: 1 | C1: 2 | D1: 3 | E1: 4 | F1: 5 | G1: 6 | H1: 7 | I1: 8 | J1: 9 | K1: 10 | L1: 11 | M1: 12 | N1: 13 | O1: 14 | P1: 15 | Q1: 16 | R1: 17 | S1: 18 | T1: 19 | U1: 20 | V1: 21 | W1: 22 | X1: 23 | Y1: 24 | Z1: 25 | AA1: 26 | AB1: 27 | AC1: 28
A3: RUT | B3: RUT2 | C3: Razon Social | D3: Ciudad | E3: Direccion | F3: Fono | G3: Vendedor | H3: Correo | I3: WWW | J3: Contacto | K3: Cargo | L3: GRUPO | M3: Credito | N3: Transporte | O3: BLOQUEADO | P3: Dcto | Q3: CONDICION DE PAGO | R3: CELULAR | S3: GIRO | T3: NOMBRE DE TIENDA | U3: COMUNA | V3: Observaciones | W3: Ped_anterior | X3: Cantidad | Y3: Despacho | Z3: Saldo | AA3: % Despacho | AB3: Valor | AC3: Meta Cole-38
A4: 4.878.758-4 | B4: 48787584 | C4: ROBERTO KOBUS PEMSO | D4: ANCUD | E4: PUDETO 143-145 | F4: 998269854 | G4: PATRICIO CUEVAS | H4: tiendasmachos@gmail.com | I4: MACHOS BOUTIQUE@SURNET.CL | J4: JENIFER PAGOS | L4: 4 | M4: 0 | N4: VARMONTT | Q4: CREDITO 30 Y 60 | S4: GRANDES TIENDAS | T4: MACHOS | U4: ANCUD | V4: VARMONTT | X4: 505 | Y4: 438 | Z4: =SUM(X4-Y4) | AA4: 0.88706366 | AB4: 11150620 | AC4: 782
A5: 5.001.562-9 | B5: 50015629 | C5: INES VARGAS PINO | D5: COPIAPO | E5: ATACAMA 461-A | F5: 52-213939 | G5: HECTOR CAFFIERO | J5: INES VARGAS | L5: 3 | M5: 0 | N5: SER VALL | P5: 0.05 | Q5: TRANSF. CONTRA FACTURA | R5: 8-8637797 | S5: TIENDA DE VESTIR | T5: BOUTIQUE GEMINIS | U5: COPIAPO | X5: 0 | Y5: 0 | Z5: =SUM(X5-Y5) | AA5: 0 | AB5: 0 | AC5: 0
A6: 5.384.900-8 | B6: 53849008 | C6: ELIANA RIQUELME R. | D6: FUTRONO | E6: BALMACEDA 249 | F6: 966322618 | G6: PATRICIO CUEVAS | J6: ELIANA RIQUELME | L6: 4 | M6: 0 | N6: TUR BUS | Q6: CREDITO 30 Y 60 | S6: VENTAS | T6: COSAS BOUTIQUE | U6: FUTRONO | X6: 0 | Y6: 0 | Z6: =SUM(X6-Y6) | AA6: 0 | AB6: 0 | AC6: 0
A7: 5.913.365-9 | B7: 59133659 | C7: ANA MARIA MANFREDI CARRASCO | D7: OVALLE | E7: VICUÑA MACKENNA 287 | F7: 053-622626 | G7: HECTOR CAFFIERO | H7: manfredi@hotmail.com | J7: DANIELA O ANA MARIA | K7: DUEÑO | L7: 3 | M7: 0 | N7: CHILE LINDO | Q7: CREDITO 30 Y 60 | S7: VENTAS AL POR MENOR | T7: BOUTIQUE PARA TI | U7: =D7 | X7: 118 | Y7: 107 | Z7: =SUM(X7-Y7) | AA7: 0.63736264 | AB7: 2688930 | AC7: 186.3
A8: 6.031.123-4 | B8: 60311234 | C8: FABIOLA BENAVENTE MEZA | D8: PARRAL | E8: ANIBAL PINTO 590 | F8: 961895384 | G8: CARLOS CUEVAS | H8: tiendaelegance@gmail.com | J8: FABIOLA BENAVENTE | K8: POP DESPACHADO 11/12 | L8: 3 | M8: 0 | N8: VILLA PRAT | Q8: CONTRAFACTURA | S8: BOUTIQUE | T8: ELEGANTE BOUTIQUE | U8: PARRAL | X8: 62 | Y8: 55 | Z8: =SUM(X8-Y8) | AA8: 0.97777778 | AB8: 1399450 | AC8: 51.75
A9: 6.331.910-4 | B9: 63319104 | C9: LUIS SOUMASTRE RAMIREZ | D9: ARICA | E9: 21 DE MAYO 454 | F9: 058-2232959 | G9: HECTOR CAFFIERO | H9: lfsr24@hotmail.com | J9: gloria tapia | L9: 3 | M9: 0 | N9: CHACON | Q9: CREDITO 30 Y 60 | S9: VENTAS AL POR MENOR | U9: ARICA | X9: 71 | Y9: 65 | Z9: =SUM(X9-Y9) | AA9: 0 | AB9: 1665350 | AC9: 26.45
A10: 6.589.904-3 | B10: 65899043 | C10: ANITA BERTA GADICKE | D10: OSORNO | E10: OHIGGINS 534 | F10: 985067217 | G10: PATRICIO CUEVAS | H10: anitagadicke@gmail.com | J10: ANITA GADICKE | L10: 4 | M10: 0 | N10: CIDHER | Q10: CREDITO 30 Y 60 | S10: BOUTIQUE | T10: ALBANY SPORT | U10: OSORNO | X10: 0 | Y10: 0 | Z10: =SUM(X10-Y10) | AA10: 0 | AB10: 0 | AC10: 0
A11: 6.775.324-0 | B11: 67753240 | C11: MARIA DE LOS ANGELES DIAZ BELLIDO | D11: VILLA ALEMANA | E11: BUENOS AIRE 845 | F11: 32-2951011 | G11: PATRICIO CUEVAS | H11: balaustros2@hotmail.com | I11: BALASUTROSVILLAALEMANA@GMAIL.C | J11: MARIA DE LOS ANGELES | L11: 4 | N11: ABC | Q11: CREDITO 30 Y 60 | S11: BOUTIQUE | T11: BALAUSTROS BOUTIQUE | U11: VILLA ALEMANA | X11: 0 | Y11: 0 | Z11: =SUM(X11-Y11) | AA11: 0 | AB11: 0 | AC11: 0
A12: 6.799.967-3 | B12: 67999673 | C12: 3 | D12: CABILDO | E12: HUMERES 727 | F12: 91286053 | G12: CARLOS CUEVAS | H12: anisalta@hotmail.com | J12: ANA MARIA SALVATIERR | L12: 3 | M12: 0 | N12: RETIRA Sn Gerardo | Q12: CREDITO 30 Y 60 | S12: BOUTIQUE | T12: BOUTIQUE ANITA | U12: CABILDO | X12: 36 | Y12: 36 | Z12: =SUM(X12-Y12) | AA12: 0.97777778 | AB12: 917640 | AC12: 216.2
A13: 76.965.431-3 | B13: 769654313 | C13: OPALO VESTUARIO | D13: CONCEPCION | E13: BARROS ARANA 815 LOCAL 14 | F13: 991959818 | G13: PATRICIO CUEVAS | H13: mayobenites@hotmail.com | J13: HILIA CONCHA | K13: DUEÑA | L13: 1 | M13: 0 | N13: CHEVALIER | Q13: CHEQUE 30 DIAS | R13: 99594046 | S13: BOUTIQUE | T13: OPALO BOUTIQUE | U13: CONCEPCION | V13: HIJA MARJORIE BENITEZ, TRANSPORTE CHEVALIER 13/11 | X13: 704 | Y13: 555 | Z13: =SUM(X13-Y13) | AA13: 0.70772443 | AB13: 14347450 | AC13: 635.95
A14: 7.096.837-1 | B14: 70968371 | C14: GLORIA CECILIA OLIVARES TORRES | D14: CHAÑARAL | E14: MERINO JARPA 590 | F14: 09-98175762 | G14: HECTOR CAFFIERO | H14: g.oltorres91@gmail.com | J14: DANIEL CEA COMPRA Y | L14: 1 | M14: 0 | N14: TUR BUS | Q14: CREDITO 30 Y 60 | S14: TIENDA | T14: EVEN EZER | U14: CHAÑARAL | X14: 130 | Y14: 125 | Z14: =SUM(X14-Y14) | AA14: 0.88983051 | AB14: 3238750 | AC14: 143.75
A15: 7.562.033-0 | B15: 75620330 | C15: PATRICIA BARRIA MANCILLA | D15: PORVENIR | E15: JOHN WILLIAMS 034 | F15: 061-2580171 | G15: SERGIO KRAMARENCO | H15: patricia.barria@gmail.com | J15: PATRICIA BARRIA | N15: TRANSCARGO | Q15: CREDITO 30 Y 60 | T15: ROMY'S | U15: PORVENIR | X15: 0 | Y15: 0 | Z15: =SUM(X15-Y15) | AA15: 0 | AB15: 0 | AC15: 0
A16: 7.634.829-4 | B16: 76348294 | C16: CARLOS MELLA ALVARADO | D16: CASTRO | E16: OHIGGINS 658 | F16: 065-2637291 | G16: PATRICIO CUEVAS | H16: tiendamodafiel@gmail.com | J16: SEÑORA SOFIA | L16: 3 | N16: CRUZ DEL SUR | P16: 0 | Q16: CONTRAFACTURA | R16: 9-5791119 | S16: TIENDA Y PAQUETERIA | T16: MODA FIEL | U16: CASTRO | X16: 259 | Y16: 221 | Z16: =SUM(X16-Y16) | AA16: 0.73799127 | AB16: 5596790 | AC16: 248.4
A17: 7.675.412-8 | B17: 76754128 | C17: IRMA ROMERO CASTRO | D17: CURANILAHUE | E17: ARTURO PRAT 1384 | F17: 041/2691287 | G17: PATRICIO CUEVAS | H17: irmafranciscaromero@gmail.com | I17: IRMAFRANCISCAROMERO@GMAIL.COM | J17: IRMA ROMERO | K17: POP DESPACHADO 12/12 | L17: 3 | M17: 0 | N17: CHEVALIER | Q17: CREDITO 30 Y 60 | S17: BOUTIQUE | T17: FRANCISCA ROMERO BOUTIQUE | U17: CURANILAHUE | X17: 0 | Y17: 0 | Z17: =SUM(X17-Y17) | AA17: 0 | AB17: 0 | AC17: 0
A18: 8.259.662-3 | B18: 82596623 | C18: LUIGI ZANDONAI | D18: LA SERENA | E18: BALMACEDA 423 | F18: 51-215122 | G18: HECTOR CAFFIERO | H18: luigizandonay@hotmail.com | J18: LUIGI ZANDONAI | K18: POP DESPACHADO 12/12 | L18: 3 | M18: 0 | N18: PIERO | Q18: CREDITO 30 Y 60 | S18: TIENDA | T18: TIENDA LUIGI ZANDONAI | U18: =D18 | X18: 0 | Y18: 0 | Z18: =SUM(X18-Y18) | AA18: 0 | AB18: 0 | AC18: 48.3
A19: 8.611.778-9 | B19: 86117789 | C19: EMILIA PALMA VILCHES | D19: SAN JAVIER | E19: ARTURO PRAT 2365 | F19: 73-2322862 | G19: CARLOS CUEVAS | H19: mily.palma@gmail.com | J19: MILY PALMA | K19: DUEÑA | L19: 1 | M19: 0 | N19: GEMITA | Q19: CREDITO 30 Y 60 | S19: GRANDES TIENDAS | T19: MILY | U19: SAN JAVIER | V19: SIN INFORMACION COMERCIAL 20/02 | X19: 0 | Y19: 0 | Z19: =SUM(X19-Y19) | AA19: 0 | AB19: 0 | AC19: 0
A20: 8.659.812-4 | B20: 86598124 | C20: RODRIGO EDUARDO SEÑOR LEDESMA | D20: TOME | E20: NOGUEIRA 1137 | F20: 41-2651720 9860610 | G20: PATRICIO CUEVAS | H20: senrodtom@hotmail.com | J20: RODRIGO SEÑOR O MONI | K20: SOCIO | L20: 3 | M20: 0 | N20: VILLA PEAT | Q20: CREDITO 30 Y 60 | S20: VTAS DE PRENDAS DE VESTIR | T20: COMERCIAL LOGROÑO | U20: TOME | V20: SIN INFORMACION COMERCIAL 20/02 | X20: 0 | Y20: 0 | Z20: =SUM(X20-Y20) | AA20: 0 | AB20: 0 | AC20: 0
A21: 8.673.204-1 | B21: 86732041 | C21: ROMAN JUAN CASTRO CAYO | D21: ARICA | E21: AVENIDA 18 DE SEPTIEMBRE 301 L | F21: 58-2232504 | G21: HECTOR CAFFIERO | H21: castro.jade@hotmail.com | J21: ROMAN CASTRO | L21: 1 | M21: 0 | N21: TUR BUS | P21: 0.05 | Q21: CREDITO 30 DIAS | S21: CALZADOS Y ROPAS DE VESTIR | U21: ARICA | X21: 41 | Y21: 42 | Z21: =SUM(X21-Y21) | AA21: 0.76041667 | AB21: 1057580 | AC21: 60.95
A22: 8.780.898-K | B22: 8780898K | C22: PATRICIA HAFON DESMOND | D22: TOCOPILLA | E22: 21 DE MAYO 1549 | F22: 55-812319 | G22: HECTOR CAFFIERO | H22: phafond@hotmail.com | J22: PATRICIA HAFFON | K22: CRISTINA PAGOS | L22: 1 | M22: 0 | N22: RAMOS CHOLELE | Q22: CREDITO 30 Y 60 | S22: BOUTIQUE | U22: =D22 | X22: 8 | Y22: 0 | Z22: =SUM(X22-Y22) | AA22: 0 | AB22: 0 | AC22: 0
A23: 8.837.310-3 | B23: 88373103 | C23: MARIA FRANCISCA IDE SCHMIDT | D23: LA REINA | E23: CARLOS SILVA VILDOSOLA 93 | F23: 2 27586405 | G23: PATRICIO CUEVAS | H23: franciscaides@hotmail.com | J23: SRA FRANCISCA | K23: POP DESPACHADO 11/12 | L23: 3 | M23: 0 | N23: TUR BUS | Q23: CREDITO 30 Y 60 | S23: BOUTIQUE | T23: BOUTIQUE FRANCISCA IDE | U23: LA REINA | X23: 0 | Y23: 0 | Z23: =SUM(X23-Y23) | AA23: 0 | AB23: 0 | AC23: 0
A24: 8.875.220-1 | B24: 88752201 | C24: ANA MARIA CORTES | D24: HUASCO | E24: PEDRO AGUIRRE CERDA 316 | F24: 51-531308 | G24: HECTOR CAFFIERO | H24: cgonza77@hotmail.com | J24: CARLA GONZALEZ | L24: 2 | M24: 0 | N24: TUR BUS | Q24: CREDITO30 DIAS | S24: TIENDA BAZAR Y PAQUETERIA | T24: ANA MARIA BOUTIQUE | U24: =D24 | X24: 0 | Y24: 0 | Z24: =SUM(X24-Y24) | AA24: 0 | AB24: 0 | AC24: 0
A25: 8.990.492-7 | B25: 89904927 | C25: LEYLA DEL CAMPO CASTRO | D25: PUERTO AYSEN | E25: ARTURO PRAT 735 | F25: 067-336824 | G25: SERGIO KRAMARENCO | H25: oleyboutique@gmail.com | J25: LEYLA DEL CAMPO | K25: DUEÑA DE LA TIENDA | L25: 3 | M25: 0 | N25: ATE | Q25: TRANSF. CONTRA ENTREGA | S25: BOUTIQUE | T25: OLEY BOUTIQUE | U25: PUERTO AYSEN | X25: 0 | Y25: 0 | Z25: =SUM(X25-Y25) | AA25: 0 | AB25: 0 | AC25: 0
A26: 9.016.604-2 | B26: 90166042 | C26: RODRIGO SALDIVIA REMOLCOY | D26: QUELLON | E26: LADRILLERO 075 | F26: 65/682901 65/683414 | G26: PATRICIO CUEVAS | H26: lucre_esve1@hotmail.com | J26: LUCRESIA ESCANDON | K26: POP DESPACHADO 12/12 | L26: 4 | M26: 0 | N26: CRUZ DEL SUR | Q26: CREDITO 30 Y 60 | X26: 0 | Y26: 0 | Z26: =SUM(X26-Y26) | AA26: 0 | AB26: 0 | AC26: 0
A27: 9.276.152-5 | B27: 92761525 | C27: CARMEN GLORIA GALLARDO VALERIO | D27: LA UNION | E27: COMERCIO 400 | F27: 64-425041 | G27: PATRICIO CUEVAS | H27: ricardo_lmunoz@yahoo.com | J27: RICARDO MUÑOZ | K27: POP DESPACHADO 12/12 | L27: 3 | M27: 0 | N27: CHEVALIER | Q27: CREDITO 30 Y 60 | S27: TIENDA | T27: PIBAS | U27: LA UNION | X27: 121 | Y27: 106 | Z27: =SUM(X27-Y27) | AA27: 0.71031746 | AB27: 2771940 | AC27: 287.5
A28: 9.305.252-8 | B28: 93052528 | C28: SABINA QUISPE PAIRO | D28: ARICA | E28: 18 SEPTIEMBRE 301 LOCAL 4 | F28: 58-251824 LOCAL | G28: HECTOR CAFFIERO | H28: constanzacontreras1310@gmail.com | J28: SABINA QUISPE | K28: MARLON ZAPATA | L28: 1 | M28: 0 | N28: CHACON | Q28: CREDITO 30 Y 60 | S28: BOUTIQUE | T28: SABY SPORT | U28: ARICA | X28: 553 | Y28: 441 | Z28: =SUM(X28-Y28) | AA28: 0.87244898 | AB28: 11312590 | AC28: 439.3
A29: 9.434.963-K | B29: 9434963K | C29: ROSA EMILIA FUENTES MANCILLA | D29: QUEILEN | E29: PEDRO AGUIRRE CERDA 183 | F29: 65/611209 611543 | G29: PATRICIO CUEVAS | H29: rosa.fuentes.23@gmail.com | J29: ROSA FUENTES MANCILL | K29: VERONICA PAGOS | L29: 3 | M29: 0 | N29: CRUZ DEL SUR | Q29: TRANSF. CONTRA ENTREGA | S29: TIENDA | T29: TIENDA Y PAQUETERIA ROCIO | U29: QUEILEN | X29: 0 | Y29: 0 | Z29: =SUM(X29-Y29) | AA29: 0 | AB29: 0 | AC29: 0
A30: 9.684.131-0 | B30: 96841310 | C30: NEDY BASCUNAN MANSILLA | D30: COYHAIQUE | E30: ERRAZURIZ 261-A | F30: 67-245741 | G30: SERGIO KRAMARENCO | H30: nedybascunan@gmail.com | J30: NEDY | K30: 41619 | L30: 1 | M30: 0 | N30: TRANSMAX | Q30: CONTADO | S30: TIENDA | T30: BOUTIQUE FRANCHESCA | U30: COYHAIQUE | X30: 0 | Y30: 0 | Z30: =SUM(X30-Y30) | AA30: 0 | AB30: 0 | AC30: 345
A31: 9.804.121-4 | B31: 98041214 | C31: MARIA CONCHA CACERES | D31: CONSTITUCION | E31: VIAL 380 A | F31: 71-2673006 | G31: PATRICIO CUEVAS | H31: mariaconcha-63@hotmail.co | J31: MARIA CONCHA CACERES | K31: DUEÑA | L31: 3 | M31: 0 | N31: EMECOL | Q31: CREDITO 30 Y 60 | S31: TIENDA | T31: TRIBAL | U31: CONSTITUCION | X31: 0 | Y31: 0 | Z31: =SUM(X31-Y31) | AA31: 0 | AB31: 0 | AC31: 0
A32: 10.026.410-2 | B32: 100264102 | C32: GLORIA CONTRERAS TORRES | D32: COCHRANNE | E32: RIO COLONIAL 560 | F32: 67-552734 | G32: SERGIO KRAMARENCO | H32: gcontrerastorres@hotmail.cl | J32: GLORIA CONTRERAS | L32: 3 | M32: 0 | N32: ATE | Q32: TRANSF. CONTRA ENTREGA | S32: VENTAS PRENDAS DE VESTIR | U32: COCHRANE | V32: DICOM OK AL 27/2 | X32: 0 | Y32: 0 | Z32: =SUM(X32-Y32) | AA32: 0 | AB32: 0 | AC32: 37.95
A33: 10.270.508-4 | B33: 102705084 | C33: ELIANA VENTURELLI REGLA | D33: CAP. PASTENE | E33: PEDRO MONTT 640 | F33: 84092579 | G33: PATRICIO CUEVAS | H33: elianaventurelliregla@hotmail. | J33: ELIANA VENTURELLI | K33: POP DESPACHADO 12/12 | L33: 3 | M33: 0 | N33: JC | Q33: CHEQUE 30 DIAS | S33: BOUTIQUE | U33: TRAIGUEN | V33: SIN INFORMACION COMERCIAL 20/02 | X33: 190 | Y33: 121 | Z33: =SUM(X33-Y33) | AA33: 0.96875 | AB33: 3051790 | AC33: 36.8
A34: 10.529.776-9 | B34: 105297769 | C34: OLGA OLIVIA POBLETE CONCHA | D34: TRAIGUEN | E34: LAGOS 957 | F34: 950866511 | G34: CARLOS CUEVAS | H34: OLGAPOBLETECONCHA@GMAIL.COM | J34: OLGA POBLETE | L34: 3 | N34: BUSES JC | Q34: TRANSF. CONTRAFACTURA | R34: 0 | S34: BOUTIQUE | T34: FENIX BOUTIQUE | X34: 96 | Y34: 70 | Z34: =SUM(X34-Y34) | AA34: 0.72916667 | AB34: 2423040 | AC34: 70.15
A35: 10.777.684-2 | B35: 107776842 | C35: KETTY ROJAS RAMIREZ | D35: COPIAPO | E35: VILLA DIEGO PORTALES C/11 | F35: 052/241236 | G35: HECTOR CAFFIERO | H35: krojasramirez@gmail.com | L35: 4 | M35: 0 | N35: ENVIAS EXPRESS | Q35: CREDITO 30 Y 60 | S35: TIENDA | X35: 0 | Y35: 0 | Z35: =SUM(X35-Y35) | AA35: 0 | AB35: 0 | AC35: 0
A36: 10.879.819-K | B36: 10879819K | C36: CELIA VASQUEZ BARRERA | D36: VILLARRICA | E36: PEDRO DE VALDIVIA 650 LOCAL 25 | F36: 045-2412431 | G36: PATRICIO CUEVAS | H36: prodigos@live.cl | J36: CELIA VASQUEZ | K36: POP DESPACHADO 11/12 | L36: 1 | M36: 0 | N36: TUR BUS | P36: 0.05 | Q36: CONTADO | T36: PRODIGOS | U36: VILLARRICA | V36: NO CUMPLE PERFIL PARA MOHICANO | X36: 49 | Y36: 40 | Z36: =SUM(X36-Y36) | AA36: 0.96551724 | AB36: 1006600 | AC36: 49.45
A37: 11.354.049-4 | B37: 113540494 | C37: PATRICIA MENA SANDOVAL | D37: TRAIGUEN | E37: AV SAAVEDRA 460 | F37: 045-861873 | G37: PATRICIO CUEVAS | H37: patcemesa@hotmail.com | J37: PATRICIA MENA | L37: 3 | M37: 0 | Q37: CREDITO 30 Y 60 | S37: BOUTIQUE | T37: PATY MENA BOUTIQUE | U37: TRAIGUEN | X37: 0 | Y37: 0 | Z37: =SUM(X37-Y37) | AA37: 0 | AB37: 0 | AC37: 0
A38: 11.407.997-9 | B38: 114079979 | C38: DANITZA OSSES AEDO | D38: TRAIGUEN | E38: CALLE SANTA CRUZ Nº 807 | F38: 45-861192 | G38: PATRICIO CUEVAS | H38: danitzaosses@hotmail.com | J38: DANITZA OSSES | K38: DUEÑA | L38: 3 | M38: 0 | Q38: CREDITO 30 Y 60 | V38: TRANSPORTES JAC , SIN INFORMES COMERCIALES 20/02 | X38: 106 | Y38: 95 | Z38: =SUM(X38-Y38) | AA38: 0.8630137 | AB38: 2438050 | AC38: 50.6
A39: 11.564.359-2 | B39: 115643592 | C39: BELLA FUENTES PINCHEIRA | D39: LINARES | E39: CHACABUCO 435 LOCAL 03 | F39: 73-2219931 | G39: PATRICIO CUEVAS | H39: befupi@gmail.com | J39: BELLA FUENTES | K39: POP DESPACHADO 12/12 | L39: 1 | M39: 0 | N39: CHEVALIER | P39: 0.05 | Q39: CONTADO | R39: 98376422 | S39: BOUTIQUE BAZAR Y PAQUETERIA | T39: D JAVI | U39: LINARES | V39: CANCELA CHEQUE 30 DIAS CON 10% DE DESCUENTO, SU ENCARGADA DE LOCAL ES MINERVA | X39: 623 | Y39: 497 | Z39: =SUM(X39-Y39) | AA39: 0.92916667 | AB39: 12767030 | AC39: 500.25
A40: 11.684.129-0 | B40: 116841290 | C40: HUGO MONTERO FIGUEROA | D40: LOS ANGELES | E40: VALDIVIA 487 LOCAL L | G40: PATRICIO CUEVAS | H40: hugomonterof@yahoo.es | J40: HUGO MONTERO | K40: DUEÑO | L40: 1 | M40: 0 | N40: CHEVALIER | Q40: 30 DIAS | R40: 09-3447832 | S40: TIENDAS | T40: HECHIZOS | U40: LOS ANGELES | V40: TRANSPORTE CHEVALIER | X40: 397 | Y40: 380 | Z40: =SUM(X40-Y40) | AA40: 0.98507463 | AB40: 9639200 | AC40: 385.25
A41: 12.003.736-6 | B41: 120037366 | C41: ARMANDO BARRIA LEGUE | D41: PUERTO NATALES | E41: MANUEL BULNES 731 LOCAL A | F41: 061-413977 | G41: SERGIO KRAMARENCO | H41: tiendarmando@gmial.com | J41: ARMANDO BARRIA | L41: 3 | M41: 0 | N41: TRANSCARGO | Q41: TRANSF. CONTRA ENTREGA | S41: TIENDA | T41: ESPACIO JEANS | U41: PUERTO NATALES | X41: 70 | Y41: 57 | Z41: =SUM(X41-Y41) | AA41: 0.99450549 | AB41: 1447430 | AC41: 218.5
A42: 12.323.239-9 | B42: 123232399 | C42: MABEL ALEJANDRA MUNOZ MOLINER | D42: ANGOL | E42: CAUPOLICAN 341 LOCAL 1 | F42: 45-717973 | G42: PATRICIO CUEVAS | H42: comercialpaucoma@gmail.co | J42: MABEL MUÑOZ | K42: POP RECHAZADO 12/12 | L42: 3 | M42: 0 | N42: TUR BUS | Q42: CONTADO | S42: BOUTIQUE | T42: BOUTIQUE PAULA | U42: ANGOL | V42: SIN INFORMACION COMERCIAL 20/02 | X42: 0 | Y42: 0 | Z42: =SUM(X42-Y42) | AA42: 0 | AB42: 0 | AC42: 0
A43: 12.495.320-0 | B43: 124953200 | C43: RODRIGO BARRENA ARAVENA | D43: MELIPILLA | E43: SERRANO 395 LOCAL 211 | F43: 97491171 | G43: RICHARD CUEVAS | L43: 1 | N43: PROPIO | Q43: CONTADO | R43: 0 | T43: BOUTIQUE CANELA Y MIEL | X43: 0 | Y43: 0 | Z43: =SUM(X43-Y43) | AA43: 0 | AB43: 0 | AC43: 0
A44: 12.838.491-K | B44: 12838491K | C44: JESSICA ARAYA CEPEDA | D44: ANTOFAGASTA | E44: MANUEL RODRIGUEZ 3065 | F44: 9-8640684 | G44: HECTOR CAFFIERO | H44: bebaignacia@hotmail.com | N44: TURBUS | Q44: TRANSF. CONTRA FACTURA | X44: 4 | Y44: 4 | Z44: =SUM(X44-Y44) | AA44: 0.75409836 | AB44: 103960 | AC44: 60.95
A45: 14.405.243-9 | B45: 144052439 | C45: CECILIA RIVERA ROMERO | D45: TEMUCO | E45: AV. TORREMOLINO 410 LOCAL 132 | F45: 953815405 | G45: PATRICIO CUEVAS | H45: CECILIA.MOHICANO@GMAIL.COM | J45: CECILIA RIVERA | K45: POP DESPACHADO 12/12 | L45: 1 | M45: 0 | N45: CHEVALIER | Q45: 60 - 90 DIAS | R45: 953815405 | S45: BOUTIQUE | T45: RIVERA JEANS | U45: TEMUCO | V45: TUR BUS , SIN INFORMAES COMERCIALES 20/02 | X45: 366 | Y45: 340 | Z45: =SUM(X45-Y45) | AA45: 0.67619048 | AB45: 8732600 | AC45: 608.35
A46: 14.905.682-3 | B46: 149056823 | C46: CLAUDIO TORRES VIERAS | D46: BIO-BIO | E46: DIEGO PORTALES N°1110 | F46: 950089698 | G46: CARLOS CUEVAS | H46: MARGAGONZALEZFLO@GMAIL.COM | J46: MARGARITA | L46: 1 | N46: CHEVALIER | Q46: CONTADO | S46: PAQUETERIA Y PERFUMERIA | T46: EL RINCONCITO DE LA MODA | U46: LOS ALAMOS | X46: 0 | Y46: 0 | Z46: =SUM(X46-Y46) | AA46: 0 | AB46: 0 | AC46: 16.1
A47: 15.627.315-5 | B47: 156273155 | C47: MAURICIO DONOSO MANTOYA | D47: OSORNO | E47: CHOCRANE 651 LOCAL 109 | G47: PATRICIO CUEVAS | H47: mauriciodonosomontoya@hotmail.com | J47: MAURICIO DONOSO | L47: 1 | N47: TUR BUS OFICINA | P47: 0 | Q47: CREDITO 30 Y 60 | R47: 77999446 | S47: BOUTIQUE | T47: BOUTIQUE HERRADURA | U47: OSORNO | X47: 0 | Y47: 0 | Z47: =SUM(X47-Y47) | AA47: 0 | AB47: 0 | AC47: 0
A48: 15.814.934-6 | B48: 158149346 | C48: CAROLINA DELGADO ROMERO | D48: LA LIGUA | E48: DENEBOLA 1033 | G48: CARLOS CUEVAS | Q48: CONTADO | R48: 0 | X48: 0 | Y48: 0 | Z48: =SUM(X48-Y48) | AA48: 0 | AB48: 0 | AC48: 0
A49: 16.065.905-K | B49: 16065905K | C49: PATRICIA CANALES | D49: PUNTA ARENAS | E49: BORIES 932 LOCAL 201 | F49: 09-94044305 | G49: SERGIO KRAMARENCO | H49: jorgecabett@hotmail.com | J49: NARIA OYARZUN LEIVA | L49: 3 | N49: TRANSCARGO | Q49: TRANSF. CONTRA ENTREGA | R49: 09-94044305 / 61-710598 | S49: TIENDA | T49: TIENDA JORGE CABBET | U49: PUNTA ARENAS | X49: 216 | Y49: 125 | Z49: =SUM(X49-Y49) | AA49: 0.275 | AB49: 3276750 | AC49: 124.2
A50: 16.868.500-9 | B50: 168685009 | C50: FRANKA SALAZAR MUÑOZ | D50: ANTOFAGASTA | E50: AV LLANQUIHUE 4216 D13 | F50: 055-547656 | G50: HECTOR CAFFIERO | H50: franka92@hotmail.com | J50: FRANKA SALAZAR | L50: 1 | M50: 0 | N50: TUR BUS | Q50: CREDITO 30 Y 60 | R50: 9-1595286 | S50: BOUTIQUE | T50: BOUTIQUE FRANKAS | U50: ANTOFAGASTA | V50: BLOQUEO PEDIDO X CLIENTE NO DESPACHAR FALTA FONDOS | X50: 0 | Y50: 0 | Z50: =SUM(X50-Y50) | AA50: 0 | AB50: 0 | AC50: 0
A51: 18.282.453-4 | B51: 182824534 | C51: CONSTANZA CANALES OYARZUN | D51: PUNTA ARENAS | E51: BORIES 932 LOCAL 204 | F51: 61-710598 | G51: SERGIO KRAMARENCO | H51: jorgecabett@hotmail.com | J51: MARIA OYARZUN | L51: 3 | M51: 0 | N51: TRANSCARGO | Q51: CREDITO 30 Y 60 | S51: TIENDA | T51: TIENDAS JORGE CABETT | U51: PUNTA ARENAS | X51: 0 | Y51: 0 | Z51: =SUM(X51-Y51) | AA51: 0 | AB51: 0 | AC51: 0
A52: 3.877.646-0 | B52: 38776460 | C52: LUIS CARRASCO PERALTA | D52: SAN FERNANDO | E52: CHILLAN 502 LOCAL 13 | F52: 942948977 | G52: PATRICIO CUEVAS | H52: KATTIE.CARRASCO@HOTMAIL.COM | L52: 1 | N52: ANDIMAR | Q52: CONTADO | R52: 0 | T52: TIENDAS DE VESTIR Y CALZADO | U52: SAN FERNANDO | X52: 0 | Y52: 0 | Z52: =SUM(X52-Y52) | AA52: 0 | AB52: 0 | AC52: 0
A53: 52.004.390-K | B53: 52004390K | C53: WILFREDO ROJAS QUILODR | D53: SAN CARLOS | E53: BALMACEDA 315 | F53: 42-411798 | G53: PATRICIO CUEVAS | H53: ALBANYSPORT@GMAIL.COM | L53: 3 | N53: CHEVALIER | Q53: CONTRAFACTURA | X53: 92 | Y53: 69 | Z53: =SUM(X53-Y53) | AA53: 0.84415584 | AB53: 1740310 | AC53: 115
A54: 7.295.293-6 | B54: 72952936 | C54: ANA SAAVEDRA ORTIZ | D54: CAÑETE | E54: COVADONGA 240 LOCAL 1 | F54: 41-2-611782 | G54: PATRICIO CUEVAS | H54: ANASAAVEDRAO@HOTMAIL.COM | J54: ANA SAAVEDRA | N54: CHEVALIER | Q54: CREDITO 30 Y 60 | V54: TRANSPORTE CHEVALIER , SIN INFORMES COMERCIALES 20/02 | X54: 104 | Y54: 93 | Z54: =SUM(X54-Y54) | AA54: 0.71212121 | AB54: 2418070 | AC54: 117.3
A55: 7.509.921-5 | B55: 75099215 | C55: NOLBERTO AVILA CORTES | D55: CAUQUENES | E55: PRAT 549 | F55: 976689778 | G55: PATRICIO CUEVAS | H55: NOLBERTO.E.AVLA@GMAIL.COM | J55: SRA. CECILIA | K55: DUEÑA | L55: 1 | N55: VILLA PRAT | Q55: CONTADO | R55: 0 | T55: SCARLETT BOUTIQUE | U55: CAUQUENES | X55: 166 | Y55: 163 | Z55: =SUM(X55-Y55) | AA55: 0.6969697 | AB55: 4135370 | AC55: 181.7
A56: 70.002.640-K | B56: 70002640K | C56: COOPPATRIA | D56: SANTIAGO | E56: ZENTENO 190 | F56: 02-26994660 | G56: PATRICIO CUEVAS | H56: pcaceres@coopatria.cl | J56: PAOLA CACERES | K56: PAOLA SAN MARTIN | L56: 1 | M56: 0 | Q56: CREDITO 30 Y 60 | X56: 0 | Y56: 0 | Z56: =SUM(X56-Y56) | AA56: 0 | AB56: 0 | AC56: 0
A57: 76.007.823-9 | B57: 760078239 | C57: COMERCIAL CARMEN TEMER EIRL | D57: ARAUCO | E57: ESMERALDA 365 | F57: 041-2552402 | G57: PATRICIO CUEVAS | H57: carmentemer@gmail.com | J57: CARMEN TEMER | K57: POP DESPACHADO 11/12 | L57: 3 | M57: 0 | N57: CHEVALIER | Q57: CREDITO 30 Y 60 | S57: PRENDAS DE VESTIR | T57: MULTITIENDAS TEMER | U57: ARAUCO | X57: 0 | Y57: 0 | Z57: =SUM(X57-Y57) | AA57: 0 | AB57: 0 | AC57: 0
A58: 76.013.196-2 | B58: 760131962 | C58: MARIA PILAR JEREZ Y CIA.LTDA. | D58: ANGOL | E58: JULIO SEPULVEDA 331 | F58: 45-712538 | G58: PATRICIO CUEVAS | H58: boutiqueloscisnes@gmail.com | J58: SRA PILAR JEREZ | K58: POP DESPACHADO 12/12 | L58: 3 | M58: 0 | N58: GEMITA | Q58: CONTADO | S58: BOUTIQUE | U58: ANGOL | X58: 83 | Y58: 96 | Z58: =SUM(X58-Y58) | AA58: 0.81481481 | AB58: 2446040 | AC58: 44.85
A59: 76.017.630-3 | B59: 760176303 | C59: COMERCIAL Q & M LTDA. | D59: QUELLON | E59: LADRILLEROS 247 | F59: 065-292000 | G59: PATRICIO CUEVAS | H59: malvarez@dimarsa.cl | J59: MIRIAM ALVAREZ COMPR | K59: POP DESPACHADO 12/12 | L59: 1 | M59: 0 | N59: SANCHEZ | P59: 0.05 | Q59: 6O DIAS | S59: GRANDES TIENDAS | T59: DIMARSA | U59: QUELLON | V59: TRANSPORTE SANCHEZ | X59: 364 | Y59: 356 | Z59: =SUM(X59-Y59) | AA59: 0 | AB59: 9174440 | AC59: 0
A60: 76.017.630-3 | B60: 760176303 | C60: COMERCIAL Q&MPUERTO VARAS | D60: PUERTO VARAS | E60: SALVADOR 117 | F60: 065-2292650 | G60: PATRICIO CUEVAS | H60: svargas@dimarsa.cl | J60: SANDRA VARGAS | K60: JEFA DE COMPRAS | L60: 2 | N60: SANCHEZ | Q60: 60 DIAS | S60: GRANDES TIENDAS | T60: DIMARSA | U60: PUERTO VARAS | X60: 364 | Y60: 356 | Z60: =SUM(X60-Y60) | AA60: 0 | AB60: 9174440 | AC60: 0
A61: 76.048.404-0 | B61: 760484040 | C61: SOC.COM.DON JORGE LTDA | D61: PANGUIPULLI | E61: MARTINEZ DE ROZAS 728 | F61: 063-311014-311089 | G61: PATRICIO CUEVAS | H61: jorgeflandezg@yahoo.com | J61: ALEJANDRA FLANDEZ | L61: 3 | M61: 0 | N61: TALADRIZ CARGO | Q61: 30 DIAS | R61: 88668259 | S61: COMERCIALIZADORA DE VESTUARIO | T61: DON JORGE | U61: PANGUIPULLI | V61: TRANSPORTE LA FRONTERA , SIN INFORMACION COMERCIAL 20/02 | X61: 60 | Y61: 44 | Z61: =SUM(X61-Y61) | AA61: 0 | AB61: 1099560 | AC61: 6.9
A62: 76.049.842-4 | B62: 760498424 | C62: INVERSIONES JULIAN LTDA. | D62: RENGO | E62: PRAT 325 | F62: 09-72950801 | G62: PATRICIO CUEVAS | H62: fernanda.roman@san-antonio.cl | J62: FERNANDA ROMAN | L62: 2 | M62: 0 | N62: JOKADAL | P62: 0.05 | Q62: 45 dias | S62: GRANDES TIENDAS | T62: MULTITIENDAS SAN ANTONIO | U62: RENGO | X62: 1292 | Y62: 1159 | Z62: =SUM(X62-Y62) | AA62: 0.94388778 | AB62: 29769410 | AC62: 637.1
A63: 76.067.887-2 | B63: 760678872 | C63: SOC COM SAN MARTIN Y TORRES LTDA | D63: SAN CARLOS | E63: SERRANO 544 LOCAL 1-2 | F63: 042-416759 | G63: PATRICIO CUEVAS | H63: jsanmartin@tiendaelpunto.cl | L63: 3 | M63: 0 | N63: GEMITA | Q63: CREDITO 30 Y 60 | S63: BOUTIQUE | U63: =D63 | X63: 169 | Y63: 146 | Z63: =SUM(X63-Y63) | AA63: 0 | AB63: 3709540 | AC63: 0
A64: 76.072.224-3 | B64: 760722243 | C64: SOC.COMERCIAL BOBERC LTDA. | D64: CASTRO | E64: BLANCO 169 | F64: 65-3337952 | G64: PATRICIO CUEVAS | H64: boberck ptomontt@123.cl | K64: POP DESPACHADO 12/12 | L64: 3 | M64: 0 | Q64: CREDITO 30 Y 60 | S64: GRANDES TIENDAS | U64: CASTRO | X64: 0 | Y64: 0 | Z64: =SUM(X64-Y64) | AA64: 0 | AB64: 0 | AC64: 0
A65: 76.078.517-2 | B65: 760785172 | C65: DON CRISTOBAL LTDA. | D65: LA UNION | E65: ANGAMOS 520 | F65: 064-2426901 | G65: PATRICIO CUEVAS | H65: valentinaboutique01@gmail.com | J65: DORIS SALGADO | K65: DUEÑA | N65: ECOEXX | Q65: CREDITO 30 Y 60 | R65: 98248393 | S65: BOUTIQUE | T65: VALENTINA BOUTIQUE | U65: LA UNION | X65: 0 | Y65: 0 | Z65: =SUM(X65-Y65) | AA65: 0 | AB65: 0 | AC65: 0
A66: 76.079.186-5 | B66: 760791865 | C66: CARMEN WILLIAMS RIVERA EIRL | D66: PUERTO AYSEN | E66: SARGENTO ALDEA 1160 | F66: 67-336452 | G66: SERGIO KRAMARENCO | H66: tiendajavbian@gmail.com | J66: Jorge QUINTANA | L66: 3 | N66: ATE | Q66: TRANSF. CONTRA ENTREGA | R66: 9-0507606 | V66: TRANSPORT ATE | X66: 143 | Y66: 74 | Z66: =SUM(X66-Y66) | AA66: 0.48571429 | AB66: 1904260 | AC66: 95.45
A67: 76.090.949-1 | B67: 760909491 | C67: SOCIEDAD COMERCIAL OLGA BOUTIQUE LTDA | D67: VILLARRICA | E67: CAMILO HENRIQUEZ 331-B | F67: 45-416539 | G67: PATRICIO CUEVAS | H67: olguitahermosilla@hotmail.com | J67: OLGA HERMOSILLA | N67: TUR BUS | Q67: CREDITO 30 Y 60 | S67: BOUTIQUE | T67: OLGA BOUTIQUE | U67: VILLARICA | X67: 0 | Y67: 0 | Z67: =SUM(X67-Y67) | AA67: 0 | AB67: 0 | AC67: 0
A68: 76.099.347-6 | B68: 760993476 | C68: GLADYS VALDIVIA PEREZ EIRL | D68: LA LIGUA | E68: URIBE 166 LOCAL 2 | F68: 989226623 | G68: CARLOS CUEVAS | H68: avenuelaligua@gmail.com | J68: GLADYS VALDIVIA | K68: SOCIAS | L68: 1 | M68: 0 | N68: JT | Q68: CONTADO | S68: BOUTIQUE | T68: BOUTIQUE AVENUE | U68: LA LIGUA | X68: 79 | Y68: 51 | Z68: =SUM(X68-Y68) | AA68: 0.44927536 | AB68: 1280490 | AC68: 70.15
A69: 76.121.220-6 | B69: 761212206 | C69: SOC.COM.INOSTROZA GOMEZ LTDA. | D69: COYHAIQUE | E69: PRAT 577 | F69: 67-215040 | G69: SERGIO KRAMARENCO | H69: tiendayuly@patagoniachile.cl | J69: PATRICIA GOMEZ | L69: 3 | M69: 0 | N69: FIORDOS | Q69: TRANSF. CONTRA ENTREGA | R69: 984797337 | S69: GRANDES TIENDAS | T69: TIENDAS YULY | U69: COYHAIQUE | X69: 277 | Y69: 252 | Z69: =SUM(X69-Y69) | AA69: 0.75694444 | AB69: 6335480 | AC69: 179.4
A70: 76.168.779-4 | B70: 761687794 | C70: SOCIEDAD COMERCIAL C'MUA LTDA | D70: SANTA CRUZ | E70: RAFAEL CASANOVA 132 A | F70: 72-824563 | G70: RICHARD CUEVAS | H70: tiendacmua@gmail.com | L70: 3 | N70: ANDIMAR | Q70: CONTRAENTREGA | X70: 179 | Y70: 125 | Z70: =SUM(X70-Y70) | AA70: 0.73563218 | AB70: 3197750 | AC70: 173.65
A71: 76.183.909-8 | B71: 761839098 | C71: SOCIEDAD COMERCIAL MKD CLOTHING LIMIT | D71: SANTIAGO | E71: BADAJOZ 100 OFICINA 824 | F71: 2297995 - 02-3423289 | G71: RICHARD CUEVAS | H71: cvegamartino@gmail.com | J71: CARLOS VEGA | K71: POP DESPACHADO 11/12 | L71: 4 | M71: 0 | N71: RETIRA | Q71: CREDITO 30 Y 60 | R71: 9-6459506 | S71: COMPRA VENTA PRENDAS DE VESTIR | T71: MKD LONDON CLOTHIN | U71: LAS CONDES | V71: RETIRAN AVISAR A CARLOS VEGA , SIN INFORMACION COMERCIAL 20/02 | X71: 394 | Y71: 349 | Z71: =SUM(X71-Y71) | AA71: 0.84649123 | AB71: 9101510 | AC71: 289.8
A72: 76.195.255-2 | B72: 761952552 | C72: COMERCIAL NACE SPA | D72: CASTRO | E72: SAN MARTIN 539 | F72: 961418070 | G72: PATRICIO CUEVAS | H72: e.anabalon@mawi.cl, n.anabalon@mawi.cl, VENTAS@MAWI.CL | J72: ERIKA ANABALON | N72: ECOEXX | P72: 0.05 | Q72: 60DIAS | S72: GRANDES TIENDAS | T72: MAWI | U72: CASTRO | X72: 770 | Y72: 703 | Z72: =SUM(X72-Y72) | AA72: 0.775 | AB72: 18096970 | AC72: 533.6
A73: 76.198.195-1 | B73: 761981951 | C73: COMERCIALIZADORA FACHAS Y CIA LTDA | D73: LA LIGUA | E73: ORTIZ DE ROZAS 431 | F73: 33-2713347 | G73: RICHARD CUEVAS | H73: fachasltda@hotmail.com | J73: MARIA TERESA NAVARRO | K73: POP DESPACHADO 11/12 | L73: 3 | M73: 0 | N73: TUR BUS | Q73: CREDITO 30 Y 60 | S73: VESTUARIO Y ART DE HOGAR | U73: LA LIGUA | X73: 144 | Y73: 130 | Z73: =SUM(X73-Y73) | AA73: 0.68181818 | AB73: 3272700 | AC73: 72.45
A74: 76.259.929-5 | B74: 762599295 | C74: VIOLETA LILIANA MEZA FLORES E.I.R.L. | D74: IQUIQUE | E74: VIVAR 916 | F74: 057-2391306 | G74: HECTOR CAFFIERO | H74: LILIANAMEZA@LIVE.COM | N74: Pullman Cargo | Q74: CREDITO 30 Y 60 | X74: 0 | Y74: 0 | Z74: =SUM(X74-Y74) | AA74: 0 | AB74: 0 | AC74: 0
A75: 76.339.520-0 | B75: 763395200 | C75: CONFECCIONES ARAUCO EIRL | D75: ARAUCO | E75: CONDELL 310 | F75: 412553099 | G75: PATRICIO CUEVAS | H75: tiendascycecilia@gmail.com | J75: CECILIA | L75: 4 | M75: 0 | N75: VILLA PRAT | Q75: CREDITO 30 Y 60 | S75: CONFECCIONES Y COMERZIALISACION | T75: C Y CECILIA | U75: ARAUCO | V75: TRANSPORTE VILLA PRAT , SIN INFORMACION COMERCIAL 20/02 | X75: 119 | Y75: 116 | Z75: =SUM(X75-Y75) | AA75: 0.81632653 | AB75: 2914840 | AC75: 170.2
A76: 76.368.393-1 | B76: 763683931 | C76: VIRGINIA DIAZ E HIJOS LTDA. | D76: ANGOL | E76: LAUTARO 362 2PISO | F76: 45-713425 | G76: PATRICIO CUEVAS | H76: alfredonazal@gmail.com | J76: ALFREDO NAZAL | K76: DUEÑA | L76: 3 | M76: 0 | N76: GEMITA | Q76: CREDITO 30 Y 60 | S76: TIENDA | T76: SULU | X76: 0 | Y76: 0 | Z76: =SUM(X76-Y76) | AA76: 0 | AB76: 0 | AC76: 0
A77: 76.454.354-8 | B77: 764543548 | C77: TIENDAS ALFREDO NAZAL EIRL | D77: ANGOL | E77: LAUTARO # 401 | F77: 998842676 | G77: PATRICIO CUEVAS | H77: ALFREDO NAZAL@GMAIL.COM | L77: 1 | M77: 0 | N77: GEMITA | Q77: CONTADO | S77: VENTA PRENDAS DE VESTIR | T77: COM RAIMUNDO | U77: =D77 | X77: 157 | Y77: 117 | Z77: =SUM(X77-Y77) | AA77: 0.975 | AB77: 2981830 | AC77: 164.45
A78: 76.511.829-8 | B78: 765118298 | C78: GRANDES TIENDAS CASA BROWN SPA | D78: CASTRO | E78: THOMPSON 278 | F78: 065-530546 | G78: PATRICIO CUEVAS | H78: casabrown@live.cl | J78: MARCELA | L78: 1 | M78: 0 | N78: VARMONTT | Q78: CREDITO 30 Y 60 | R78: 85874622 | S78: TIENDA | T78: CASA BROWN | U78: CASTRO | X78: 195 | Y78: 166 | Z78: =SUM(X78-Y78) | AA78: 0.73796791 | AB78: 4271340 | AC78: 218.5
A79: 76.658.950-2 | B79: 766589502 | C79: COOPELAN COMERCIAL S.A | D79: LOS ANGELES | G79: PATRICIO CUEVAS | N79: GEMITA | Q79: CREDITO 30 Y 60 | R79: 0 | X79: 477 | Y79: 402 | Z79: =SUM(X79-Y79) | AA79: 0.51595745 | AB79: 10195980 | AC79: 216.2
A80: 76.662.352-2 | B80: 766623522 | C80: ARTICULOS ELECTRONICOS NATALIA SAEZ MENDEZ E.I.R.L | D80: CHILLAN | E80: CONSTITUCION 810 LOCAL 6 | F80: 950150910 | G80: PATRICIO CUEVAS | H80: enrique.pablo.c@gmail.com | J80: NATALIA SAENZ | L80: 1 | M80: 0 | N80: CHEVALIER | Q80: 60-90 DIAS | R80: 950150910 | S80: VENTA DE PRENDAS DE VESTIR | T80: BONITA BOUTIQUE | U80: CHILLAN | V80: TRANSPORTES CHEVALIER , SIN INFORME COMERCIAL 20/02 | X80: 658 | Y80: 488 | Z80: =SUM(X80-Y80) | AA80: 0.72867587 | AB80: 12597120 | AC80: 1059.15
A81: 76.687.183-6 | B81: 766871836 | C81: NOELIA BOUTIQUE | D81: LINARES | E81: BRAZIL PORTAL ESTACION 479 LOC. 32 | F81: 987952316 | G81: RICHARD CUEVAS | H81: NOELIAGARRIDO33@GMAIL.COM | J81: NOELIA GARRIDO | K81: DUEÑA | L81: 1 | N81: CHEVALIER | Q81: 30-60 DIAS | R81: 0 | S81: BOUTIQUE | T81: NOELIA BOUTIQUE | U81: LINARES | X81: 540 | Y81: 444 | Z81: =SUM(X81-Y81) | AA81: 0.10133333 | AB81: 11290560 | AC81: 842.95
A82: 76.821.717-3 | B82: 768217173 | C82: COMERCIAL Y SERVICIOS WOLLERMANN SPA | D82: PUERTO MONTT | G82: PATRICIO CUEVAS | Q82: CONTADO | R82: 0 | X82: 0 | Y82: 0 | Z82: =SUM(X82-Y82) | AA82: 0 | AB82: 0 | AC82: 0
A83: 76.865.111-6 | B83: 768651116 | C83: SABA Y MILADE LTDA | D83: CURANILAHUE | E83: CAUPOLICAN 733 | F83: 940127841 | G83: CARLOS CUEVAS | H83: SABAYMILADE@GMAIL.COM | J83: CALUDIA METUAZE | L83: 3 | N83: CHEVALIER | Q83: TRANSF. CONTRA FACTURA | R83: 0 | X83: 0 | Y83: 0 | Z83: =SUM(X83-Y83) | AA83: 0 | AB83: 0 | AC83: 0
A84: 77.029.510-6 | B84: 770295106 | C84: SIEGMUND HNOS.LTDA. | D84: VICTORIA | E84: PISAGUA 1201 | F84: 98659430 | G84: PATRICIO CUEVAS | H84: paulafsiegmunds@gmail.com | J84: PAULA SIEGMUND | K84: PATRICIA PAGOS | L84: 1 | M84: 0 | N84: PALMA | Q84: CREDITO 30 Y 60 | S84: GRANDES TIENDAS | T84: CASA SIEGMUND | U84: VICTORIA | V84: GEMITA | X84: 252 | Y84: 219 | Z84: =SUM(X84-Y84) | AA84: 0.95833333 | AB84: 5580810 | AC84: 47.15
A85: 77.030.130-0 | B85: 770301300 | C85: DOLLY S.A. | D85: PUERTO MONTT | E85: URMENETA #292 | F85: 65-2257585 | G85: PATRICIO CUEVAS | H85: proveedores.adulto@dolly.cl | J85: ZUCETTE | K85: POP DESPACHADO 12/12 | L85: 1 | M85: 0 | N85: VARMONTT | P85: 0.05 | Q85: 30DIAS | S85: GRANDES TIENDAS | T85: DOLLY | U85: PUERTO MONTT | V85: CLIENTE CANCELA CON CHEQUE 30 DIAS 10% DESCUENTOVARMONTT | X85: 464 | Y85: 421 | Z85: =SUM(X85-Y85) | AA85: 0.93080725 | AB85: 10799790 | AC85: 691.15
A86: 77.143.280-8 | B86: 771432808 | C86: SOC.COM.JORGE ANANIAS | D86: MULCHEN | E86: VILLAGRAN 580 | F86: 998864093 | G86: CARLOS CUEVAS | H86: PILAR_ANANIAS@HOTMAIL.COM | J86: PILAR ANANIAS | K86: DUEÑA | L86: 4 | M86: 0 | N86: CHEVALIER | Q86: CREDITO30 Y 60 | S86: GRANDES TIENDAS | T86: CASA REAL | U86: MULCHEN | X86: 168 | Y86: 148 | Z86: =SUM(X86-Y86) | AA86: 0.78321678 | AB86: 3768520 | AC86: 156.4
A87: 77.326.810-K | B87: 77326810K | C87: GONART MODA LTDA. | D87: OVALLE | E87: BENAVENTE 75 | F87: 053/2625600 | G87: HECTOR CAFFIERO | H87: gonartmodas@gmail.com | N87: CHILE LINDO | Q87: CREDITO 30 Y 60 | S87: MULTITIENDA VESTUARIO | T87: GONART | U87: OVALLE | X87: 119 | Y87: 111 | Z87: =SUM(X87-Y87) | AA87: 0.8313253 | AB87: 2824890 | AC87: 115
A88: 77.359.210-1 | B88: 773592101 | C88: DICAS LTDA. | D88: CASTRO | E88: SAN MARTIN 409 | F88: 065-292650 | G88: PATRICIO CUEVAS | H88: svargas@dimarsa.cl | J88: SANDRA VARGAS | K88: POP DESPACHADO 12/12 | L88: 1 | M88: 0 | N88: SANCHEZ | Q88: 60DIAS | S88: GRANDES TIENDAS | T88: DIMARSA | U88: CASTRO | V88: TRANSPORTE SANCHEZ | X88: 0 | Y88: 0 | Z88: =SUM(X88-Y88) | AA88: 0 | AB88: 0 | AC88: 0
A89: 77.570.460-8 | B89: 775704608 | C89: COMERCIAL REGINA LTDA | D89: SANTIAGO | E89: PADRE ORELLANA 1437 | G89: PATRICIO CUEVAS | H89: AURELIO.HUILCA27@HOTMAIL.COM | L89: 4 | N89: PROPIO | Q89: CREDITO 30 Y 60 | R89: 0 | X89: 0 | Y89: 0 | Z89: =SUM(X89-Y89) | AA89: 0 | AB89: 0 | AC89: 0
A90: 77.576.530-5 | B90: 775765305 | C90: ALMACENES ELTIT LTDA | D90: PUCON | E90: OHIGGINS 292 | F90: 45-441103-379550 | G90: PATRICIO CUEVAS | J90: IVONNE OSORIO | L90: 1 | M90: 0 | N90: PROPIO | Q90: CONTADO | S90: GRANDES TIENDAS | T90: ELTIT | U90: PUCON | V90: TRANSPORTE PROPIOP | X90: 0 | Y90: 0 | Z90: =SUM(X90-Y90) | AA90: 0 | AB90: 0 | AC90: 0
A91: 77.594.510-9 | B91: 775945109 | C91: SOC.MATURANA GALVAN Y CIA.LTDA. | D91: COPIAPO | E91: ATACAMA 541 L-E | F91: 052-236479 | G91: HECTOR CAFFIERO | J91: TULIO MATURANA | K91: POP DESPACHADO 12/12 | L91: 1 | M91: 0 | N91: EXPRESS | Q91: CREDITO 30 Y 60 | S91: BOUTIQUE | T91: BOUTIQUE PILCHAS | U91: =D91 | X91: 14 | Y91: 14 | Z91: =SUM(X91-Y91) | AA91: 0 | AB91: 363860 | AC91: 8.05
A92: 77.934.770-2 | B92: 779347702 | C92: SEÑOR LEDESMA HNOS. LTDA. | D92: TOME | E92: MANUEL MONTT 1198 | F92: 041-2650083 | G92: PATRICIO CUEVAS | H92: juansenor@vtr.net | J92: JUAN SEÑOR LEDESMA | K92: POP DESPACHADO 12/12 | L92: 3 | M92: 0 | N92: VILLA PRAT | Q92: CREDITO 30 Y 60 | S92: ART DEPORTIVO | T92: COMERCIAL SEVILLA | U92: TOME | X92: 0 | Y92: 0 | Z92: =SUM(X92-Y92) | AA92: 0 | AB92: 0 | AC92: 0
A93: 78.416.190-0 | B93: 784161900 | C93: SOC.COMERCIAL BUVINIC LTDA. | D93: PUNTA ARENAS | E93: BORIES 766 | F93: 996407930 | G93: SERGIO KRAMARENCO | H93: ALEBUVINIC@GLOBALCOM.CL | I93: bingojeanspuq@hotmail.com | L93: 1 | N93: TRANSCARGO | Q93: TRANSF. CONTRA ENTREGA | R93: 9-96407930 | S93: TIENDA BAZAR | T93: BINGO JEANS | U93: PUNTA ARENAS | X93: 291 | Y93: 177 | Z93: =SUM(X93-Y93) | AA93: 0.86538462 | AB93: 4610230 | AC93: 441.6
A94: 78.801.490-2 | B94: 788014902 | C94: ALBASINI E HIJOS LIMITADA | D94: COPIAPO | E94: O'HIGGINS Nø402-420 | F94: 52-212788 | G94: HECTOR CAFFIERO | H94: franca@albasini.cl | J94: FRANCA ALBASINI | L94: 1 | M94: 0 | N94: Van Oosterwyk | Q94: CREDITO 30 Y 60 | S94: GRANDES TIENDAS | T94: ALBASINI SPORT | U94: =D94 | X94: 247 | Y94: 217 | Z94: =SUM(X94-Y94) | AA94: 0.91390728 | AB94: 5651830 | AC94: 162.15
A95: 78.840.090-K | B95: 78840090K | C95: BOUTIQUE ADIQTUS LTDA. | D95: OSORNO | E95: RAMIREZ 977 LOCAL 29 | F95: 64-201105 | G95: PATRICIO CUEVAS | H95: bveram@hotmail.com | J95: BLANCA VERA | K95: POP DESPACHADO 12/12 | L95: 2 | M95: 0 | N95: TUR BUS | Q95: 30 DÍAS | S95: BOUTIQUE | T95: BOUTIQUE ADIQTUS | U95: OSORNO | X95: 129 | Y95: 115 | Z95: =SUM(X95-Y95) | AA95: 0.88721805 | AB95: 2955850 | AC95: 188.6
A96: 79.827.960-2 | B96: 798279602 | C96: COMERCIAL LOS CARRERA LTDA | D96: COQUIMBO | E96: ALDUNATE 1138 | F96: 51-315989 | G96: HECTOR CAFFIERO | H96: sin email | J96: SRTA ISABEL | L96: 3 | M96: 0 | N96: CHILE LINDO | Q96: CREDITO 30 Y 60 | S96: BOUTIQUE | T96: BOUTIQUE TEENS | U96: =D96 | X96: 0 | Y96: 0 | Z96: =SUM(X96-Y96) | AA96: 0 | AB96: 0 | AC96: 0
A97: 79.862.960-3 | B97: 798629603 | C97: EL ARTE DE VESTIR S.A. | D97: PUNTA ARENAS | E97: ERRAZURIZ 644 | F97: 615320-615350-615370 | G97: SERGIO KRAMARENCO | H97: jaguila@elartedevestir.cl | J97: RODRIGO ALVAREZ | K97: POP DESPACHADO 11/12 | L97: 3 | M97: 0 | N97: CONOSUR | Q97: TRANSF. CONTRA ENTREGA | R97: 972386296 | S97: GRANDES TIENDAS, CALZADO, IMP | T97: EL ARTE DE VESTIR | U97: PUNTA ARENAS | X97: 240 | Y97: 234 | Z97: =SUM(X97-Y97) | AA97: 0.96744186 | AB97: 5927660 | AC97: 557.75
A98: 79.982.490-6 | B98: 799824906 | C98: COMERCIAL MULTICENTRO LTDA. | D98: TALCA | E98: AV 07 ORIENTE 1620 | F98: 71-214581 | G98: RICHARD CUEVAS | H98: MARCELOC@MULTICENTRO.CL | K98: POP DESPACHADO 12/12 | L98: 2 | M98: 0 | N98: PROPIO | Q98: CREDITO 60 DIAS | T98: MULTICENTRO | U98: TALCA | X98: 2190 | Y98: 2046 | Z98: =SUM(X98-Y98) | AA98: 0.97529412 | AB98: 51787540 | AC98: 2889.95
A99: 81.210.300-8 | B99: 812103008 | C99: JAVER HNOS Y CIA LTDA | D99: SAN ANTONIO | E99: CENTENARIO 105 | F99: 962479655 | G99: RICHARD CUEVAS | H99: M.ARMIJO@JAVER.CL | I99: M.ARMIJO@JAVER.CL | J99: M ARMIJO VENTAS | L99: 2 | M99: 0 | N99: BEZANILLA | P99: 5 | Q99: 30 DÍAS | S99: GRANDES TIENDAS | T99: JAVER | U99: =D99 | X99: 168 | Y99: 157 | Z99: =SUM(X99-Y99) | AA99: 0.80555556 | AB99: 4045430 | AC99: 173.65
A100: 81.242.500-5 | B100: 812425005 | C100: COOPERCARAB LTDA | D100: ANTOFAGASTA | E100: MAIPU 667 | F100: (55)280856 | G100: PATRICIO CUEVAS | H100: tesoreriaantofa@coopercarabc.c | L100: 2 | M100: 0 | N100: PROPIO | P100: 0.05 | Q100: 60DIAS | S100: GRANDES TIENDAS | T100: COOPERCARAB | U100: ANTOFAGASTA | X100: 367 | Y100: 330 | Z100: =SUM(X100-Y100) | AA100: 0.37467018 | AB100: 8543700 | AC100: 1179.9
A101: 81.242.500-5 | B101: 812425005 | C101: COOPERCARAB LTDA | D101: CONCEPCION | E101: BERNANDO O'HIGGINS 80 | F101: (41) 2521576 | G101: PATRICIO CUEVAS | H101: comprasmktconcep@coopercarab.c | L101: 2 | M101: 0 | N101: PROPIO | P101: 0.05 | Q101: 60DIAS | S101: GRANDES TIENDAS | T101: COOPERCARAB | U101: CONCEPCION | X101: 367 | Y101: 330 | Z101: =SUM(X101-Y101) | AA101: 0.37467018 | AB101: 8543700 | AC101: 1179.9
...

Sheet BD_COMPARATIVA
A1: RUT | B1: RAZON SOCIAL | C1: COD VEN | D1: VENDEDOR | E1: CIUDAD | F1: CANTIDAD T:38 | G1: VALOR T:38 | H1: FACTURADO T:38 | I1: VALOR FACT. T:38
A2: 48787584 | B2: ROBERTO KOBUS PEMSO | C2: 2 | D2: PATRICIO CUEVAS | E2: ANCUD | F2: 505 | G2: 12867950 | H2: 438 | I2: 11150620
A3: 59133659 | B3: ANA MARIA MANFREDI CARRASCO | C3: 6 | D3: HECTOR CAFFIERO VASQUEZ | E3: OVALLE | F3: 118 | G3: 2963820 | H3: 107 | I3: 2688930
A4: 60311234 | B4: FABIOLA BENAVENTE MEZA | C4: 12 | D4: CARLOS CUEVAS | E4: PARRAL | F4: 62 | G4: 1574380 | H4: 55 | I4: 1399450
A5: 60921830 | B5: NORA BARRAZA MILLA | C5: 6 | D5: HECTOR CAFFIERO VASQUEZ | E5: DIEGO DE ALMAGRO | F5: 67 | G5: 1737330 | H5: 60 | I5: 1562400
A6: 63319104 | B6: LUIS SOUMASTRE RAMIREZ | C6: 6 | D6: HECTOR CAFFIERO VASQUEZ | E6: ARICA | F6: 71 | G6: 1821290 | H6: 65 | I6: 1665350
A7: 67999673 | B7: ANA MARIA SALVATIERRA TAPIA | C7: 2 | D7: PATRICIO CUEVAS | E7: CABILDO | F7: 36 | G7: 917640 | H7: 36 | I7: 917640
A8: 70968371 | B8: GLORIA CECILIA OLIVARES TORRES | C8: 6 | D8: HECTOR CAFFIERO VASQUEZ | E8: CHAﾑARAL | F8: 130 | G8: 3367700 | H8: 125 | I8: 3238750
A9: 71650685 | B9: SERGIO HERNAN CERDA ESCOBAR | C9: 2 | D9: PATRICIO CUEVAS | E9: LOS ANGELES | F9: 290 | G9: 7297100 | H9: 138 | I9: 3473620
A10: 72952936 | B10: ANA SAAVEDRA ORTIZ | C10: 12 | D10: CARLOS CUEVAS | E10: CAﾑETE | F10: 104 | G10: 2694960 | H10: 93 | I10: 2418070
A11: 75099215 | B11: NOLBERTO AVILA CORTES | C11: 2 | D11: PATRICIO CUEVAS | E11: CAUQUENES | F11: 166 | G11: 4210340 | H11: 163 | I11: 4135370
A12: 76348294 | B12: CARLOS MELLA ALVARADO | C12: 2 | D12: PATRICIO CUEVAS | E12: 2 | F12: 259 | G12: 6558410 | H12: 221 | I12: 5596790
A13: 81838518 | B13: CLARA VARGAS NATER | C13: 12 | D13: CARLOS CUEVAS | E13: ANGOL | F13: 102 | G13: 2668980 | H13: 58 | I13: 1517420
A14: 86732041 | B14: ROMAN JUAN CASTRO CAYO | C14: 6 | D14: HECTOR CAFFIERO VASQUEZ | E14: ARICA | F14: 41 | G14: 1029590 | H14: 42 | I14: 1057580
A15: 8780898K | B15: PATRICIA HAFON DESMOND | C15: 6 | D15: HECTOR CAFFIERO VASQUEZ | E15: TOCOPILLA | F15: 8 | G15: 207920 | H15: 0 | I15: 0
A16: 92761525 | B16: CARMEN GLORIA GALLARDO VALERIO | C16: 2 | D16: PATRICIO CUEVAS | E16: LA UNION | F16: 121 | G16: 3165790 | H16: 106 | I16: 2771940
A17: 93052528 | B17: SABINA QUISPE PAIRO | C17: 6 | D17: HECTOR CAFFIERO VASQUEZ | E17: ARICA | F17: 553 | G17: 14187470 | H17: 441 | I17: 11312590
A18: 94411564 | B18: ANA MARIA SANCHEZ LUENGO | C18: 12 | D18: CARLOS CUEVAS | E18: PUREN | F18: 90 | G18: 2316100 | H18: 84 | I18: 2154160
A19: 96234422 | B19: MIRNA PACHECO RABANAL | C19: 2 | D19: PATRICIO CUEVAS | E19: CABRERO | F19: 228 | G19: 5836720 | H19: 198 | I19: 5030020
A20: 102705084 | B20: ELIANA VENTURELLI REGLA | C20: 12 | D20: CARLOS CUEVAS | E20: CAPITAN PASTENE | F20: 190 | G20: 4834100 | H20: 121 | I20: 3051790
A21: 105613059 | B21: MARISOL DURAN NAVARRO | C21: 12 | D21: CARLOS CUEVAS | E21: MELIPILLA | F21: 42 | G21: 1112580 | H21: 41 | I21: 1086590
A22: 10879819K | B22: CELIA VASQUEZ BARRERA | C22: 2 | D22: PATRICIO CUEVAS | E22: VILLARICA | F22: 49 | G22: 1240510 | H22: 40 | I22: 1006600
A23: 114079979 | B23: DANITZA OSSES AEDO | C23: 12 | D23: CARLOS CUEVAS | E23: TRAIGUEN | F23: 106 | G23: 2716940 | H23: 95 | I23: 2438050
A24: 115643592 | B24: BELLA FUENTES PINCHEIRA | C24: 13 | D24: RICHARD CUEVAS | E24: LINARES | F24: 623 | G24: 16052770 | H24: 497 | I24: 12767030
A25: 116841290 | B25: HUGO MONTERO FIGUEROA | C25: 2 | D25: PATRICIO CUEVAS | E25: LOS ANGELES | F25: 397 | G25: 10084030 | H25: 380 | I25: 9639200
A26: 120037366 | B26: ARMANDO BARRIA LEGUE | C26: 3 | D26: SERGIO KRAMARENCO | E26: PUERTO NATALES | F26: 70 | G26: 1772300 | H26: 57 | I26: 1447430
A27: 123737024 | B27: ISVELDA MELO ACEVEDO | C27: 2 | D27: PATRICIO CUEVAS | E27: LINARES | F27: 18 | G27: 467820 | H27: 0 | I27: 0
A28: 12838491K | B28: JESSICA ARAYA CEPEDA | C28: 6 | D28: HECTOR CAFFIERO VASQUEZ | E28: ANTOFAGASTA | F28: 4 | G28: 103960 | H28: 4 | I28: 103960
A29: 136381334 | B29: KAREN HUAMAN LOPEZ | C29: 6 | D29: HECTOR CAFFIERO VASQUEZ | E29: ARICA | F29: 11 | G29: 296890 | H29: 11 | I29: 296890
A30: 137440369 | B30: CARLA ALIAGA | C30: 6 | D30: HECTOR CAFFIERO VASQUEZ | E30: VALLENAR | F30: 192 | G30: 4942080 | H30: 163 | I30: 4191370
A31: 138622045 | B31: PAOLA NAVARRO | C31: 6 | D31: HECTOR CAFFIERO VASQUEZ | E31: ARICA | F31: 48 | G31: 1253520 | H31: 22 | I31: 571780
A32: 139701321 | B32: GLORIA GALINDO PEREZ | C32: 3 | D32: SERGIO KRAMARENCO | E32: COYHAIQUE | F32: 250 | G32: 6409500 | H32: 240 | I32: 6159600
A33: 143849244 | B33: MONICA SANDOVAL NAVARRETE | C33: 2 | D33: PATRICIO CUEVAS | E33: COLLIPULLI | F33: 92 | G33: 2329080 | H33: 92 | I33: 2335080
A34: 144052439 | B34: CECILIA RIVERA ROMERO | C34: 2 | D34: PATRICIO CUEVAS | E34: TEMUCO | F34: 366 | G34: 9408340 | H34: 340 | I34: 8732600
A35: 144967860 | B35: CRISTIAN ALEJANDRO FUENTES FLORES | C35: 12 | D35: CARLOS CUEVAS | E35: RANCAGUA | F35: 359 | G35: 9313410 | H35: 228 | I35: 5950720
A36: 146351107 | B36: CAROLINA MIRANDA | C36: 12 | D36: CARLOS CUEVAS | E36: SANTA CRUZ | F36: 304 | G36: 7886960 | H36: 269 | I36: 6956310
A37: 154536493 | B37: MARITZA TOSSO CATRICURA | C37: 3 | D37: SERGIO KRAMARENCO | E37: PANGUIPULLI | F37: 44 | G37: 1111560 | H37: 20 | I37: 511800
A38: 16065905K | B38: PATRICIA CANALES OYARZUN | C38: 3 | D38: SERGIO KRAMARENCO | E38: PUNTA ARENAS | F38: 216 | G38: 5676840 | H38: 125 | I38: 3276750
A39: 162593110 | B39: KATERIN FRANCHESCA CASANGA SANTANA | C39: 6 | D39: HECTOR CAFFIERO VASQUEZ | E39: CALAMA | F39: 214 | G39: 5603860 | H39: 125 | I39: 3258750
A40: 162603744 | B40: JETZABEL AGUIRRE ALVAREZ | C40: 6 | D40: HECTOR CAFFIERO VASQUEZ | E40: CALAMA | F40: 446 | G40: 11605540 | H40: 396 | I40: 10290040
A41: 196950281 | B41: GABRIELA MANSILLA WUPPEELMANN | C41: 3 | D41: SERGIO KRAMARENCO | E41: PUNTA ARENAS | F41: 164 | G41: 4262360 | H41: 149 | I41: 3876510
A42: 52004390K | B42: WILFREDO ROJAS QUILODRAN EIRL | C42: 12 | D42: CARLOS CUEVAS | E42: SAN CARLOS | F42: 92 | G42: 2341080 | H42: 69 | I42: 1740310
A43: 760094900 | B43: COMERCIAL DIANCU LTDA. | C43: 2 | D43: PATRICIO CUEVAS | E43: ANCUD | F43: 182 | G43: 4660180 | H43: 165 | I43: 4205350
A44: 760131962 | B44: MARIA PILAR JEREZ Y CIA.LTDA. | C44: 12 | D44: CARLOS CUEVAS | E44: ANGOL | F44: 83 | G44: 2114170 | H44: 96 | I44: 2446040
A45: 760176303 | B45: COMERCIAL Q & M LTDA | C45: 2 | D45: PATRICIO CUEVAS | E45: LA UNION | F45: 364 | G45: 9376360 | H45: 356 | I45: 9174440
A46: 760381810 | B46: SOCIEDAD COMERCIAL ARS LTDA. | C46: 12 | D46: CARLOS CUEVAS | E46: YUNGAY | F46: 96 | G46: 2471040 | H46: 82 | I46: 2120180
A47: 760484040 | B47: SOC.COM. DON JORGE LTDA | C47: 2 | D47: PATRICIO CUEVAS | E47: PANGUIPULLI | F47: 60 | G47: 1511400 | H47: 44 | I47: 1099560
A48: 760498424 | B48: INVERSIONES JULIAN S.A. | C48: 13 | D48: RICHARD CUEVAS | E48: RENGO | F48: 1292 | G48: 33221080 | H48: 1159 | I48: 29769410
A49: 760678872 | B49: SOC COM SAN MARTIN Y TORRES LTDA | C49: 2 | D49: PATRICIO CUEVAS | E49: SAN CARLOS | F49: 169 | G49: 4288310 | H49: 146 | I49: 3709540
A50: 760791865 | B50: COMERCIAL JAVBIAN SPA | C50: 3 | D50: SERGIO KRAMARENCO | E50: PUERTO AYSEN | F50: 143 | G50: 3677570 | H50: 74 | I50: 1904260
A51: 760993476 | B51: GLADYS VALDIVIA PEREZ EIRL | C51: 12 | D51: CARLOS CUEVAS | E51: LA LIGUA | F51: 79 | G51: 1980210 | H51: 51 | I51: 1280490
A52: 761212206 | B52: SOC. COM. INOSTROZA GOMEZ LTDA. | C52: 3 | D52: SERGIO KRAMARENCO | E52: COYHAIQUE | F52: 277 | G52: 6961230 | H52: 252 | I52: 6335480
A53: 761687794 | B53: SOCIEDAD COMERCIAL C'MUA LIMITADA | C53: 13 | D53: RICHARD CUEVAS | E53: SANTA CRUZ | F53: 179 | G53: 4557210 | H53: 125 | I53: 3197750
A54: 761839098 | B54: SOCIEDAD COMERCIAL MKD CLOTHING LIMITADA | C54: 2 | D54: PATRICIO CUEVAS | E54: SANTIAGO | F54: 394 | G54: 10268060 | H54: 349 | I54: 9101510
... A60: 764058496 | B60: COMERCIAL LE PETIT BOUTIQUE | C60: 2 | D60: PATRICIO CUEVAS | E60: LA CALERA | F60: 127 | G60: 3291730 | H60: 127 | I60: 3291730
A61: 76415150K | B61: COMERCIAL CHELECH S.A. | C61: 3 | D61: SERGIO KRAMARENCO | E61: PUERTO NATALES | F61: 144 | G61: 3706560 | H61: 133 | I61: 3429670
A62: 76421739K | B62: COMERCIAL DIWEB LTDA | C62: 2 | D62: PATRICIO CUEVAS | E62: PUERTO MONTT | F62: 324 | G62: 8204760 | H62: 287 | I62: 7280130
A63: 764509315 | B63: COMERCIAL ACTUAL SPA | C63: 13 | D63: RICHARD CUEVAS | E63: SANTA CRUZ | F63: 132 | G63: 3430680 | H63: 129 | I63: 3355710
A64: 764543548 | B64: GRANDES TIENDAS ALFREDO NAZAL SPA | C64: 12 | D64: CARLOS CUEVAS | E64: ANGOL | F64: 157 | G64: 4023430 | H64: 117 | I64: 2981830
A65: 765118298 | B65: GRANDES TIENDAS CASA BROWN SPA | C65: 2 | D65: PATRICIO CUEVAS | E65: CASTRO | F65: 195 | G65: 4999050 | H65: 166 | I65: 4271340
A66: 765183685 | B66: COMERCIALIZADORA HERNANDO GUZMAN ROJAS | C66: 6 | D66: HECTOR CAFFIERO VASQUEZ | E66: COQUIMBO | F66: 35 | G66: 896650 | H66: 33 | I66: 846670
A67: 766400809 | B67: MULTITIENDAS DIAYSEN lIMITADA | C67: 2 | D67: PATRICIO CUEVAS | E67: PUERTO AYSEN | F67: 266 | G67: 6857340 | H67: 258 | I67: 6649420
A68: 766518486 | B68: FORCAEL INOSTROZA LTD | C68: 2 | D68: PATRICIO CUEVAS | E68: LOS ANGELES | F68: 780 | G68: 19898200 | H68: 704 | I68: 17953960
A69: 766589502 | B69: COOPELAN COMERCIAL S.A | C69: 2 | D69: PATRICIO CUEVAS | E69: LOS ANGELES | F69: 477 | G69: 12150230 | H69: 402 | I69: 10195980
A70: 766623522 | B70: SOCIEDAD COMERCIAL NATALIAS SAEZ SPA | C70: 2 | D70: PATRICIO CUEVAS | E70: CHILLAN | F70: 658 | G70: 16993420 | H70: 488 | I70: 12597120
A71: 766871836 | B71: NOELIA BOUTIQUE | C71: 13 | D71: RICHARD CUEVAS | E71: LINARES | F71: 540 | G71: 13782600 | H71: 444 | I71: 11290560
A72: 767469861 | B72: COMERCIAL E INMOBILIRIA RAPALLO S.P.A | C72: 6 | D72: HECTOR CAFFIERO VASQUEZ | E72: IQUIQUE | F72: 40 | G72: 1016600 | H72: 40 | I72: 1016600
A73: 767756089 | B73: VTA. PRENDAS DE VESTIR SALLY LTDA | C73: 6 | D73: HECTOR CAFFIERO VASQUEZ | E73: LA SERENA | F73: 293 | G73: 7554070 | H73: 262 | I73: 6752380
A74: 768243794 | B74: BOUTIQUE LA HERRADURA LIMITADA | C74: 2 | D74: PATRICIO CUEVAS | E74: OSORNO | F74: 104 | G74: 2702960 | H74: 68 | I74: 1785320
... A88: 772090390 | B88: DUSAN SPA | C88: 2 | D88: PATRICIO CUEVAS | E88: CHILLAN | F88: 445 | G88: 11487550 | H88: 241 | I88: 6172590
A89: 77226836K | B89: CAMILA BOUTIQUE SPA | C89: 6 | D89: HECTOR CAFFIERO VASQUEZ | E89: LA SERENA | F89: 79 | G89: 2004210 | H89: 72 | I89: 1828280
A90: 77297650K | B90: ADECOM LTDA. | C90: 1 | D90: JORGE CUEVAS | E90: SANTIAGO | F90: 3 | G90: 77970 | H90: 0 | I90: 0
A91: 77326810K | B91: GONART MODAS LTDA | C91: 6 | D91: HECTOR CAFFIERO VASQUEZ | E91: OVALLE | F91: 119 | G91: 3032810 | H91: 111 | I91: 2824890
A92: 774518029 | B92: BOUTIQUE JUANA ELIZABETH ARAYA CAMPUSANO EIRL | C92: 6 | D92: HECTOR CAFFIERO VASQUEZ | E92: OVALLE | F92: 291 | G92: 7498090 | H92: 257 | I92: 6607430
A93: 774998772 | B93: COMERCIAL CASA DE PIEDRA LIMITADA | C93: 3 | D93: SERGIO KRAMARENCO | E93: PUERTO AYSEN | F93: 10 | G93: 259900 | H93: 10 | I93: 259900
A94: 775142286 | B94: COMERCIAL JOSE ANDRES CARRASCO CID EIRL | C94: 2 | D94: PATRICIO CUEVAS | E94: SAN FERNANDO | F94: 273 | G94: 7084270 | H94: 187 | I94: 4800130
A95: 775196882 | B95: DIVINA BOUTIQUE SPA | C95: 12 | D95: CARLOS CUEVAS | E95: NACIMIENTO | F95: 110 | G95: 2792900 | H95: 68 | I95: 1737320
A96: 775867256 | B96: COMERCIAL GUARDIA SPA | C96: 2 | D96: PATRICIO CUEVAS | E96: SAN JAVIER | F96: 30 | G96: 779700 | H96: 29 | I96: 752710
A97: 775945109 | B97: SOC. MATURANA GALVAN Y CIA.LTDA. | C97: 6 | D97: HECTOR CAFFIERO VASQUEZ | E97: COPIAPO | F97: 14 | G97: 363860 | H97: 14 | I97: 363860
A98: 776161667 | B98: BOUTIQUE EXCLUSIVA GIVE COYHAIQUE SPA. | C98: 3 | D98: SERGIO KRAMARENCO | E98: COYHAIQUE | F98: 63 | G98: 1584370 | H98: 62 | I98: 1559380
A99: 776449733 | B99: BOUTIQUE BIGNONIA SPA | C99: 2 | D99: PATRICIO CUEVAS | E99: QUILLOTA | F99: 75 | G99: 1957250 | H99: 58 | I99: 1518420
A100: 776506435 | B100: ANDREA ALARCON SPA | C100: 6 | D100: HECTOR CAFFIERO VASQUEZ | E100: ARICA | F100: 18 | G100: 461820 | H100: 0 | I100: 0
A101: 777307800 | B101: MANUFACTURAS E IMP.TITANIUM CHILE S.P.A | C101: 10 | D101: ANGELICA MELLA | E101: SANTIAGO | F101: 799 | G101: 20698010 | H101: 625 | I101: 16077750
A102: 779115070 | B102: NAYRA NYR SPA | C102: 2 | D102: PATRICIO CUEVAS | E102: PARRAL | F102: 96 | G102: 2447040 | H102: 86 | I102: 2197140
A103: 779568032 | B103: SOCIEDAD COMERCIAL JORGE CABETT LTDA. | C103: 3 | D103: SERGIO KRAMARENCO | E103: PUNTA ARENAS | F103: 484 | G103: 12719160 | H103: 399 | I103: 10501010
... A106: 788014902 | B106: ALBASINI E HIJOS LIMITADA | C106: 6 | D106: HECTOR CAFFIERO VASQUEZ | E106: COPIAPO | F106: 247 | G106: 6380530 | H106: 217 | I106: 5651830
A107: 78840090K | B107: BOUTIQUE ADIQTUS LTDA. | C107: 2 | D107: PATRICIO CUEVAS | E107: OSORNO | F107: 129 | G107: 3320710 | H107: 115 | I107: 2955850
A108: 798629603 | B108: EL ARTE DE VESTIR S.P.A | C108: 3 | D108: SERGIO KRAMARENCO | E108: PUNTA ARENAS | F108: 240 | G108: 6077600 | H108: 234 | I108: 5927660
A109: 799824906 | B109: COMERCIAL MULTICENTRO LTDA. | C109: 42 | D109: MULTICENTRO | E109: TALCA | F109: 2190 | G109: 55418100 | H109: 2046 | I109: 51787540
A110: 808569000 | B110: SOC.COM.E INMOB. SANTOLAYA HNOS LTDA. | C110: 6 | D110: HECTOR CAFFIERO VASQUEZ | E110: ANTOFAGASTA | F110: 98 | G110: 2463020 | H110: 92 | I110: 2313080
A111: 812103008 | B111: JAVER HNOS Y CIA LTDA | C111: 13 | D111: RICHARD CUEVAS | E111: SANTIAGO | F111: 168 | G111: 4328320 | H111: 157 | I111: 4045430
A112: 812425005 | B112: COOPERCARAB | C112: 2 | D112: PATRICIO CUEVAS | E112: CHILLAN | F112: 367 | G112: 9501330 | H112: 330 | I112: 8543700
A113: 820166000 | B113: HADWEH HERMANOS LTDA | C113: 12 | D113: CARLOS CUEVAS | E113: SAN JAVIER | F113: 152 | G113: 3811480 | H113: 133 | I113: 3323670
A114: 837158001 | B114: SOC.FLORES ALMANDOZ NAIR Y CIA LTDA | C114: 13 | D114: RICHARD CUEVAS | E114: VALLENAR | F114: 108 | G114: 2782920 | H114: 91 | I114: 2353090
A115: 856907007 | B115: COMERCIAL GERMANI SPA. | C115: 13 | D115: RICHARD CUEVAS | E115: LINARES | F115: 1254 | G115: 32154460 | H115: 1102 | I115: 28166980
A116: 869336009 | B116: EVITA LTDA. | C116: 2 | D116: PATRICIO CUEVAS | E116: CONCEPCION | F116: 50 | G116: 1249500 | H116: 49 | I116: 1224510
A117: 892586004 | B117: ESTABLECIMIENTOS GERMANI SPA | C117: 13 | D117: RICHARD CUEVAS | E117: TALCA | F117: 481 | G117: 12363190 | H117: 454 | I117: 11679460
A118: 929460006 | B118: ESTAB. COMERC. SEIDEMANN | C118: 2 | D118: PATRICIO CUEVAS | E118: LA CALERA | F118: 640 | G118: 16482600 | H118: 534 | I118: 13672660
A119: 932240009 | B119: DISTRIB. IMPORT. DIMARSA LTDA | C119: 2 | D119: PATRICIO CUEVAS | E119: PUERTO MONTT | F119: 1848 | G119: 47623520 | H119: 1781 | I119: 45855190

Sheet TRAYECTORIA
A1: CLIENTES DE TRAYECTORIA
A3: N° | B3: CLIENTES | C3: DESCUENTO
A4: 1 | B4: COMERCIAL GERMANI | C4: 0.05
A5: 2 | B5: ESTABLECIMIENTO GERMANI | C5: 0.05
A6: 3 | B6: SEIDEMAN | C6: 0.05
A7: 4 | B7: MULTICENTRO | C7: -
A8: 5 | B8: INV JULIAN | C8: 0.05
A9: 6 | B9: JAVER HNOS | C9: 0.05
A10: 7 | B10: COMERCIAL NACE | C10: 0.05
A11: 8 | B11: ALMACENES ELTIT | C11: 0.05
A12: 9 | B12: DOLLY | C12: 0.05
A13: 10 | B13: ROBERTO KOBUS | C13: 0.05

Sheet DESCUENTO COLE 18
A2: DESCUENTO COLE 18 (10/09/2021) POR PAGO DE CONTADO
B4: N° | C4: CLIENTES | D4: DESCUENTO
B5: 1 | C5: SOC.FLORES ALMANDOZ NA | D5: 0.05
B6: 2 | C6: FORCAEL | D6: 0.05
B7: 3 | C7: DOLLY | D7: 0.05
B8: 4 | C8: ROBERTO KOBUS | D8: 0.05
B9: 5 | C9: DUSAN | D9: 0.05
B10: 6 | C10: HUGO MONTERO | D10: 0.05
B11: 7 | C11: GRAN AVENTURA | D11: 0.05
B12: 8 | C12: SOC. COM. DON JORGE | D12: 0.05
B13: 9 | C13: MIRNA PACHECO | D13: 0.05
B14: 10 | C14: SABINA QUISPE | D14: 0.05
B15: 11 | C15: WILFREDO ROJAS | D15: 0.05
B16: 12 | C16: SOC COMERCIAL CMUA | D16: 0.05
... B37: 33 | C37: BOUTIQUE LA HERRADURA | D37: 0.05

Sheet CONTRAFACTURA
A1: CLIENTES DE TRAYECTORIA
A3: N° | B3: CLIENTES | C3: DESCUENTO
A4: 1 | B4: COMERCIAL GERMANI | C4: 0.05
A5: 2 | B5: ESTABLECIMIENTO GERMANI | C5: 0.05
A6: 3 | B6: SEIDEMAN | C6: 0.05
A7: 4 | B7: MULTICENTRO | C7: -
A8: 5 | B8: INV JULIAN | C8: 0.05
A9: 6 | B9: JAVER HNOS | C9: 0.05
A10: 7 | B10: COMERCIAL NACE | C10: 0.05
A11: 8 | B11: ALMACENES ELTIT | C11: 0.05
A12: 9 | B12: DOLLY | C12: 0.05
A13: 10 | B13: ROBERTO KOBUS | C13: 0.05
